[
  {
    "year": 2025,
    "month": "December",
    "month_num": 12,
    "return_pct": -0.10286173794779634,
    "ending_equity": 16342.014000000005,
    "start_date": "2025-12-01",
    "end_date": "2025-12-31"
  },
  {
    "year": 2025,
    "month": "November",
    "month_num": 11,
    "return_pct": -0.010334172845655312,
    "ending_equity": 18215.71400000001,
    "start_date": "2025-11-01",
    "end_date": "2025-11-30"
  },
  {
    "year": 2025,
    "month": "October",
    "month_num": 10,
    "return_pct": -0.04499183160074113,
    "ending_equity": 18405.924000000006,
    "start_date": "2025-10-01",
    "end_date": "2025-10-31"
  },
  {
    "year": 2025,
    "month": "September",
    "month_num": 9,
    "return_pct": 0.03247854584914021,
    "ending_equity": 19273.053999999996,
    "start_date": "2025-09-01",
    "end_date": "2025-09-30"
  },
  {
    "year": 2025,
    "month": "August",
    "month_num": 8,
    "return_pct": 0.7159929414299748,
    "ending_equity": 18666.784,
    "start_date": "2025-08-01",
    "end_date": "2025-08-31"
  },
  {
    "year": 2025,
    "month": "July",
    "month_num": 7,
    "return_pct": 0.08729006585236451,
    "ending_equity": 10878.123999999998,
    "start_date": "2025-07-01",
    "end_date": "2025-07-31"
  },
  {
    "year": 2025,
    "month": "June",
    "month_num": 6,
    "return_pct": 0.016999523256251144,
    "ending_equity": 10004.803999999998,
    "start_date": "2025-06-01",
    "end_date": "2025-06-30"
  }
]