{
  "ticker": "REGN",
  "name": "REGN",
  "sector": "Unknown",
  "description": "Investment Thesis available in report.",
  "history": [
    {
      "date": "2024-12-02",
      "open": 750.01,
      "high": 763.89,
      "low": 748.4074,
      "close": 762.34
    },
    {
      "date": "2024-12-03",
      "open": 758.53,
      "high": 770.0,
      "low": 747.565,
      "close": 749.57
    },
    {
      "date": "2024-12-04",
      "open": 748.56,
      "high": 756.1297,
      "low": 744.14,
      "close": 754.26
    },
    {
      "date": "2024-12-05",
      "open": 751.55,
      "high": 768.02,
      "low": 749.685,
      "close": 767.9
    },
    {
      "date": "2024-12-06",
      "open": 768.64,
      "high": 778.12,
      "low": 765.16,
      "close": 778.0
    },
    {
      "date": "2024-12-09",
      "open": 777.0,
      "high": 800.99,
      "low": 773.0,
      "close": 788.0
    },
    {
      "date": "2024-12-10",
      "open": 784.1,
      "high": 791.49,
      "low": 762.695,
      "close": 778.5
    },
    {
      "date": "2024-12-11",
      "open": 778.15,
      "high": 781.32,
      "low": 766.865,
      "close": 773.0
    },
    {
      "date": "2024-12-12",
      "open": 773.12,
      "high": 778.7346,
      "low": 740.46,
      "close": 740.97
    },
    {
      "date": "2024-12-13",
      "open": 738.45,
      "high": 740.17,
      "low": 728.68,
      "close": 731.3
    },
    {
      "date": "2024-12-16",
      "open": 730.52,
      "high": 739.39,
      "low": 722.23,
      "close": 724.87
    },
    {
      "date": "2024-12-17",
      "open": 721.37,
      "high": 744.8,
      "low": 721.082,
      "close": 740.01
    },
    {
      "date": "2024-12-18",
      "open": 735.21,
      "high": 745.0,
      "low": 712.3,
      "close": 714.62
    },
    {
      "date": "2024-12-19",
      "open": 711.0,
      "high": 714.05,
      "low": 693.0,
      "close": 708.25
    },
    {
      "date": "2024-12-20",
      "open": 710.2,
      "high": 717.6099,
      "low": 700.83,
      "close": 701.85
    },
    {
      "date": "2024-12-23",
      "open": 708.38,
      "high": 718.19,
      "low": 706.16,
      "close": 715.13
    },
    {
      "date": "2024-12-24",
      "open": 712.3,
      "high": 720.0,
      "low": 706.15,
      "close": 714.47
    },
    {
      "date": "2024-12-26",
      "open": 709.08,
      "high": 718.4899,
      "low": 709.08,
      "close": 716.68
    },
    {
      "date": "2024-12-27",
      "open": 710.52,
      "high": 718.99,
      "low": 709.09,
      "close": 712.4
    },
    {
      "date": "2024-12-30",
      "open": 708.04,
      "high": 708.965,
      "low": 700.4155,
      "close": 702.59
    },
    {
      "date": "2024-12-31",
      "open": 703.9,
      "high": 713.0,
      "low": 703.3862,
      "close": 712.33
    },
    {
      "date": "2025-01-02",
      "open": 720.86,
      "high": 726.81,
      "low": 711.92,
      "close": 715.19
    },
    {
      "date": "2025-01-03",
      "open": 716.07,
      "high": 722.0,
      "low": 714.76,
      "close": 718.15
    },
    {
      "date": "2025-01-06",
      "open": 715.0,
      "high": 733.69,
      "low": 713.75,
      "close": 716.26
    },
    {
      "date": "2025-01-07",
      "open": 716.34,
      "high": 734.44,
      "low": 716.34,
      "close": 730.3
    },
    {
      "date": "2025-01-08",
      "open": 728.04,
      "high": 743.28,
      "low": 725.6,
      "close": 733.59
    },
    {
      "date": "2025-01-10",
      "open": 721.33,
      "high": 724.73,
      "low": 691.0,
      "close": 696.88
    },
    {
      "date": "2025-01-13",
      "open": 669.24,
      "high": 717.37,
      "low": 666.2485,
      "close": 716.9
    },
    {
      "date": "2025-01-14",
      "open": 714.01,
      "high": 715.98,
      "low": 686.0,
      "close": 690.87
    },
    {
      "date": "2025-01-15",
      "open": 700.61,
      "high": 712.6,
      "low": 698.2,
      "close": 703.43
    },
    {
      "date": "2025-01-16",
      "open": 701.04,
      "high": 706.54,
      "low": 691.33,
      "close": 693.23
    },
    {
      "date": "2025-01-17",
      "open": 705.34,
      "high": 707.48,
      "low": 680.89,
      "close": 681.58
    },
    {
      "date": "2025-01-21",
      "open": 687.46,
      "high": 692.93,
      "low": 681.52,
      "close": 687.8
    },
    {
      "date": "2025-01-22",
      "open": 689.77,
      "high": 699.88,
      "low": 677.68,
      "close": 680.03
    },
    {
      "date": "2025-01-23",
      "open": 680.54,
      "high": 696.19,
      "low": 678.28,
      "close": 694.64
    },
    {
      "date": "2025-01-24",
      "open": 688.74,
      "high": 693.84,
      "low": 675.11,
      "close": 675.79
    },
    {
      "date": "2025-01-27",
      "open": 676.73,
      "high": 698.45,
      "low": 676.73,
      "close": 684.71
    },
    {
      "date": "2025-01-28",
      "open": 682.11,
      "high": 690.302,
      "low": 678.13,
      "close": 686.33
    },
    {
      "date": "2025-01-29",
      "open": 685.96,
      "high": 697.57,
      "low": 682.325,
      "close": 687.27
    },
    {
      "date": "2025-01-30",
      "open": 688.31,
      "high": 689.62,
      "low": 674.33,
      "close": 683.08
    },
    {
      "date": "2025-01-31",
      "open": 677.29,
      "high": 687.9999,
      "low": 671.96,
      "close": 672.98
    },
    {
      "date": "2025-02-03",
      "open": 668.8,
      "high": 673.65,
      "low": 663.4302,
      "close": 666.85
    },
    {
      "date": "2025-02-04",
      "open": 650.0,
      "high": 709.98,
      "low": 642.0,
      "close": 697.05
    },
    {
      "date": "2025-02-05",
      "open": 708.8,
      "high": 729.25,
      "low": 700.01,
      "close": 716.72
    },
    {
      "date": "2025-02-06",
      "open": 713.42,
      "high": 734.265,
      "low": 713.42,
      "close": 722.07
    },
    {
      "date": "2025-02-07",
      "open": 726.46,
      "high": 731.42,
      "low": 709.55,
      "close": 710.0
    },
    {
      "date": "2025-02-10",
      "open": 714.45,
      "high": 719.78,
      "low": 688.92,
      "close": 690.36
    },
    {
      "date": "2025-02-11",
      "open": 680.63,
      "high": 680.79,
      "low": 664.19,
      "close": 665.46
    },
    {
      "date": "2025-02-12",
      "open": 659.96,
      "high": 670.98,
      "low": 655.85,
      "close": 663.86
    },
    {
      "date": "2025-02-13",
      "open": 665.46,
      "high": 677.69,
      "low": 661.9381,
      "close": 674.27
    },
    {
      "date": "2025-02-14",
      "open": 678.2,
      "high": 684.0,
      "low": 671.55,
      "close": 673.6
    },
    {
      "date": "2025-02-18",
      "open": 679.64,
      "high": 689.95,
      "low": 674.88,
      "close": 680.0
    },
    {
      "date": "2025-02-19",
      "open": 675.29,
      "high": 688.67,
      "low": 675.29,
      "close": 685.66
    },
    {
      "date": "2025-02-20",
      "open": 688.05,
      "high": 703.1436,
      "low": 685.45,
      "close": 696.02
    },
    {
      "date": "2025-02-21",
      "open": 697.93,
      "high": 704.08,
      "low": 693.07,
      "close": 700.33
    },
    {
      "date": "2025-02-24",
      "open": 703.93,
      "high": 725.0,
      "low": 700.4301,
      "close": 713.25
    },
    {
      "date": "2025-02-25",
      "open": 720.0,
      "high": 739.0,
      "low": 715.5,
      "close": 723.47
    },
    {
      "date": "2025-02-26",
      "open": 721.29,
      "high": 721.405,
      "low": 701.07,
      "close": 706.94
    },
    {
      "date": "2025-02-27",
      "open": 705.9,
      "high": 721.0,
      "low": 700.67,
      "close": 702.78
    },
    {
      "date": "2025-02-28",
      "open": 701.32,
      "high": 708.58,
      "low": 693.71,
      "close": 698.74
    },
    {
      "date": "2025-03-03",
      "open": 701.91,
      "high": 704.6449,
      "low": 683.46,
      "close": 684.87
    },
    {
      "date": "2025-03-04",
      "open": 688.48,
      "high": 697.455,
      "low": 672.5,
      "close": 675.49
    },
    {
      "date": "2025-03-05",
      "open": 673.98,
      "high": 692.79,
      "low": 673.15,
      "close": 687.15
    },
    {
      "date": "2025-03-06",
      "open": 683.1,
      "high": 701.0,
      "low": 682.255,
      "close": 698.44
    },
    {
      "date": "2025-03-07",
      "open": 698.63,
      "high": 729.7499,
      "low": 696.43,
      "close": 707.51
    },
    {
      "date": "2025-03-10",
      "open": 710.01,
      "high": 748.29,
      "low": 709.38,
      "close": 744.83
    },
    {
      "date": "2025-03-11",
      "open": 746.7,
      "high": 747.6987,
      "low": 712.39,
      "close": 718.16
    },
    {
      "date": "2025-03-12",
      "open": 709.94,
      "high": 712.455,
      "low": 683.425,
      "close": 689.5
    },
    {
      "date": "2025-03-13",
      "open": 687.43,
      "high": 698.945,
      "low": 677.34,
      "close": 680.61
    },
    {
      "date": "2025-03-14",
      "open": 680.61,
      "high": 686.98,
      "low": 657.0,
      "close": 666.87
    },
    {
      "date": "2025-03-17",
      "open": 668.26,
      "high": 679.83,
      "low": 664.675,
      "close": 678.42
    },
    {
      "date": "2025-03-18",
      "open": 678.0,
      "high": 678.27,
      "low": 664.3,
      "close": 664.96
    },
    {
      "date": "2025-03-19",
      "open": 663.67,
      "high": 674.57,
      "low": 659.03,
      "close": 672.36
    },
    {
      "date": "2025-03-20",
      "open": 670.0,
      "high": 674.83,
      "low": 662.33,
      "close": 662.62
    },
    {
      "date": "2025-03-21",
      "open": 658.0,
      "high": 661.0,
      "low": 651.06,
      "close": 658.48
    },
    {
      "date": "2025-03-24",
      "open": 660.0,
      "high": 667.46,
      "low": 655.3,
      "close": 661.0
    },
    {
      "date": "2025-03-25",
      "open": 662.45,
      "high": 662.5699,
      "low": 633.1,
      "close": 634.14
    },
    {
      "date": "2025-03-26",
      "open": 634.14,
      "high": 644.0,
      "low": 629.02,
      "close": 640.14
    },
    {
      "date": "2025-03-27",
      "open": 641.21,
      "high": 643.43,
      "low": 629.94,
      "close": 635.83
    },
    {
      "date": "2025-03-28",
      "open": 638.01,
      "high": 642.97,
      "low": 631.45,
      "close": 637.36
    },
    {
      "date": "2025-03-31",
      "open": 630.08,
      "high": 640.72,
      "low": 618.505,
      "close": 634.23
    },
    {
      "date": "2025-04-01",
      "open": 630.51,
      "high": 641.24,
      "low": 615.0,
      "close": 617.0
    },
    {
      "date": "2025-04-02",
      "open": 613.53,
      "high": 628.0,
      "low": 610.1001,
      "close": 625.6
    },
    {
      "date": "2025-04-03",
      "open": 626.25,
      "high": 628.0,
      "low": 607.88,
      "close": 610.64
    },
    {
      "date": "2025-04-04",
      "open": 610.65,
      "high": 612.99,
      "low": 572.0,
      "close": 573.45
    },
    {
      "date": "2025-04-07",
      "open": 569.2,
      "high": 591.545,
      "low": 557.8288,
      "close": 572.78
    },
    {
      "date": "2025-04-08",
      "open": 579.46,
      "high": 586.03,
      "low": 546.36,
      "close": 556.81
    },
    {
      "date": "2025-04-09",
      "open": 538.0,
      "high": 580.73,
      "low": 525.99,
      "close": 576.72
    },
    {
      "date": "2025-04-10",
      "open": 568.93,
      "high": 571.99,
      "low": 529.725,
      "close": 546.39
    },
    {
      "date": "2025-04-11",
      "open": 548.63,
      "high": 555.53,
      "low": 533.26,
      "close": 554.18
    },
    {
      "date": "2025-04-14",
      "open": 560.44,
      "high": 574.72,
      "low": 555.3901,
      "close": 571.06
    },
    {
      "date": "2025-04-15",
      "open": 568.55,
      "high": 575.2,
      "low": 553.0,
      "close": 557.91
    },
    {
      "date": "2025-04-16",
      "open": 557.0,
      "high": 561.83,
      "low": 544.5,
      "close": 549.28
    },
    {
      "date": "2025-04-17",
      "open": 548.07,
      "high": 564.205,
      "low": 545.0001,
      "close": 563.16
    },
    {
      "date": "2025-04-21",
      "open": 556.04,
      "high": 570.35,
      "low": 552.965,
      "close": 561.49
    },
    {
      "date": "2025-04-22",
      "open": 565.5,
      "high": 587.1,
      "low": 565.14,
      "close": 585.49
    },
    {
      "date": "2025-04-23",
      "open": 595.87,
      "high": 603.77,
      "low": 584.45,
      "close": 587.85
    },
    {
      "date": "2025-04-24",
      "open": 590.93,
      "high": 601.28,
      "low": 586.81,
      "close": 599.76
    },
    {
      "date": "2025-04-25",
      "open": 598.33,
      "high": 602.79,
      "low": 585.78,
      "close": 602.64
    },
    {
      "date": "2025-04-28",
      "open": 603.36,
      "high": 614.83,
      "low": 601.19,
      "close": 610.86
    },
    {
      "date": "2025-04-29",
      "open": 561.75,
      "high": 579.98,
      "low": 542.44,
      "close": 568.91
    },
    {
      "date": "2025-04-30",
      "open": 579.26,
      "high": 600.2,
      "low": 566.985,
      "close": 598.76
    },
    {
      "date": "2025-05-01",
      "open": 589.77,
      "high": 593.935,
      "low": 578.5,
      "close": 590.0
    },
    {
      "date": "2025-05-02",
      "open": 600.0,
      "high": 615.609,
      "low": 599.08,
      "close": 605.61
    },
    {
      "date": "2025-05-05",
      "open": 606.89,
      "high": 611.04,
      "low": 601.805,
      "close": 603.58
    },
    {
      "date": "2025-05-06",
      "open": 601.01,
      "high": 606.87,
      "low": 557.64,
      "close": 558.52
    },
    {
      "date": "2025-05-07",
      "open": 561.79,
      "high": 568.1302,
      "low": 556.3602,
      "close": 560.93
    },
    {
      "date": "2025-05-08",
      "open": 547.88,
      "high": 552.5742,
      "low": 520.5,
      "close": 547.67
    },
    {
      "date": "2025-05-09",
      "open": 549.0,
      "high": 552.84,
      "low": 527.13,
      "close": 527.78
    },
    {
      "date": "2025-05-12",
      "open": 543.82,
      "high": 577.985,
      "low": 535.29,
      "close": 575.63
    },
    {
      "date": "2025-05-13",
      "open": 571.45,
      "high": 575.05,
      "low": 558.45,
      "close": 574.16
    },
    {
      "date": "2025-05-14",
      "open": 576.35,
      "high": 580.56,
      "low": 567.585,
      "close": 571.36
    },
    {
      "date": "2025-05-15",
      "open": 576.13,
      "high": 585.26,
      "low": 564.9075,
      "close": 584.99
    },
    {
      "date": "2025-05-16",
      "open": 588.23,
      "high": 595.19,
      "low": 581.49,
      "close": 594.32
    },
    {
      "date": "2025-05-19",
      "open": 588.48,
      "high": 598.56,
      "low": 586.6803,
      "close": 596.54
    },
    {
      "date": "2025-05-20",
      "open": 595.01,
      "high": 615.4454,
      "low": 595.01,
      "close": 614.79
    },
    {
      "date": "2025-05-21",
      "open": 613.055,
      "high": 617.52,
      "low": 597.9192,
      "close": 604.62
    },
    {
      "date": "2025-05-22",
      "open": 603.2,
      "high": 605.5,
      "low": 592.725,
      "close": 596.85
    },
    {
      "date": "2025-05-23",
      "open": 586.85,
      "high": 591.64,
      "low": 582.37,
      "close": 588.34
    },
    {
      "date": "2025-05-27",
      "open": 603.09,
      "high": 608.17,
      "low": 590.805,
      "close": 603.26
    },
    {
      "date": "2025-05-28",
      "open": 603.26,
      "high": 606.0,
      "low": 590.15,
      "close": 591.85
    },
    {
      "date": "2025-05-29",
      "open": 597.06,
      "high": 605.73,
      "low": 591.02,
      "close": 605.39
    },
    {
      "date": "2025-05-30",
      "open": 517.655,
      "high": 519.78,
      "low": 485.0,
      "close": 490.28
    },
    {
      "date": "2025-06-02",
      "open": 491.09,
      "high": 502.5633,
      "low": 481.58,
      "close": 490.81
    },
    {
      "date": "2025-06-03",
      "open": 490.785,
      "high": 501.11,
      "low": 485.34,
      "close": 487.86
    },
    {
      "date": "2025-06-04",
      "open": 491.71,
      "high": 499.9,
      "low": 482.99,
      "close": 484.93
    },
    {
      "date": "2025-06-05",
      "open": 486.0,
      "high": 491.77,
      "low": 476.4869,
      "close": 483.07
    },
    {
      "date": "2025-06-06",
      "open": 485.54,
      "high": 499.88,
      "low": 485.0001,
      "close": 493.22
    },
    {
      "date": "2025-06-09",
      "open": 498.0,
      "high": 518.27,
      "low": 494.42,
      "close": 517.6
    },
    {
      "date": "2025-06-10",
      "open": 520.0,
      "high": 529.99,
      "low": 518.16,
      "close": 523.53
    },
    {
      "date": "2025-06-11",
      "open": 525.77,
      "high": 528.368,
      "low": 516.1,
      "close": 518.6
    },
    {
      "date": "2025-06-12",
      "open": 517.23,
      "high": 525.22,
      "low": 512.97,
      "close": 521.84
    },
    {
      "date": "2025-06-13",
      "open": 518.25,
      "high": 529.55,
      "low": 514.98,
      "close": 529.24
    },
    {
      "date": "2025-06-16",
      "open": 532.88,
      "high": 538.2,
      "low": 520.22,
      "close": 522.68
    },
    {
      "date": "2025-06-17",
      "open": 519.27,
      "high": 523.01,
      "low": 508.7,
      "close": 508.86
    },
    {
      "date": "2025-06-18",
      "open": 508.51,
      "high": 519.17,
      "low": 503.25,
      "close": 513.58
    },
    {
      "date": "2025-06-20",
      "open": 521.05,
      "high": 521.31,
      "low": 506.38,
      "close": 509.72
    },
    {
      "date": "2025-06-23",
      "open": 510.0,
      "high": 516.18,
      "low": 507.605,
      "close": 511.92
    },
    {
      "date": "2025-06-24",
      "open": 515.79,
      "high": 527.45,
      "low": 515.79,
      "close": 522.27
    },
    {
      "date": "2025-06-25",
      "open": 521.4,
      "high": 525.63,
      "low": 516.9854,
      "close": 520.29
    },
    {
      "date": "2025-06-26",
      "open": 520.0,
      "high": 524.52,
      "low": 514.79,
      "close": 521.0
    },
    {
      "date": "2025-06-27",
      "open": 521.79,
      "high": 531.21,
      "low": 517.39,
      "close": 521.0
    },
    {
      "date": "2025-06-30",
      "open": 520.21,
      "high": 526.075,
      "low": 518.9,
      "close": 525.0
    },
    {
      "date": "2025-07-01",
      "open": 523.97,
      "high": 548.035,
      "low": 521.0,
      "close": 534.91
    },
    {
      "date": "2025-07-02",
      "open": 533.66,
      "high": 551.5,
      "low": 529.69,
      "close": 547.74
    },
    {
      "date": "2025-07-03",
      "open": 547.75,
      "high": 555.0,
      "low": 546.61,
      "close": 547.36
    },
    {
      "date": "2025-07-07",
      "open": 546.0,
      "high": 547.59,
      "low": 532.6,
      "close": 538.11
    },
    {
      "date": "2025-07-08",
      "open": 538.87,
      "high": 559.46,
      "low": 537.45,
      "close": 547.75
    },
    {
      "date": "2025-07-09",
      "open": 547.1,
      "high": 558.38,
      "low": 545.38,
      "close": 552.58
    },
    {
      "date": "2025-07-10",
      "open": 554.38,
      "high": 566.365,
      "low": 550.11,
      "close": 559.76
    },
    {
      "date": "2025-07-11",
      "open": 558.39,
      "high": 568.46,
      "low": 551.48,
      "close": 567.74
    },
    {
      "date": "2025-07-14",
      "open": 566.1,
      "high": 575.13,
      "low": 562.0,
      "close": 570.59
    },
    {
      "date": "2025-07-15",
      "open": 574.15,
      "high": 574.75,
      "low": 546.28,
      "close": 547.96
    },
    {
      "date": "2025-07-16",
      "open": 550.0,
      "high": 558.35,
      "low": 546.57,
      "close": 547.93
    },
    {
      "date": "2025-07-17",
      "open": 545.67,
      "high": 554.4799,
      "low": 542.01,
      "close": 550.0
    },
    {
      "date": "2025-07-18",
      "open": 550.0,
      "high": 550.885,
      "low": 541.5,
      "close": 542.52
    },
    {
      "date": "2025-07-21",
      "open": 543.44,
      "high": 552.98,
      "low": 542.5,
      "close": 545.53
    },
    {
      "date": "2025-07-22",
      "open": 546.92,
      "high": 563.0,
      "low": 546.92,
      "close": 560.93
    },
    {
      "date": "2025-07-23",
      "open": 568.12,
      "high": 576.7,
      "low": 563.005,
      "close": 572.39
    },
    {
      "date": "2025-07-24",
      "open": 572.54,
      "high": 577.7299,
      "low": 563.67,
      "close": 564.64
    },
    {
      "date": "2025-07-25",
      "open": 565.41,
      "high": 567.2103,
      "low": 555.5,
      "close": 563.1
    },
    {
      "date": "2025-07-28",
      "open": 563.53,
      "high": 567.9483,
      "low": 558.54,
      "close": 558.63
    },
    {
      "date": "2025-07-29",
      "open": 558.0,
      "high": 559.61,
      "low": 552.0,
      "close": 558.145
    },
    {
      "date": "2025-07-30",
      "open": 560.45,
      "high": 563.59,
      "low": 550.49,
      "close": 554.58
    },
    {
      "date": "2025-07-31",
      "open": 550.01,
      "high": 558.13,
      "low": 541.6125,
      "close": 545.46
    },
    {
      "date": "2025-08-01",
      "open": 583.01,
      "high": 583.28,
      "low": 542.89,
      "close": 558.87
    },
    {
      "date": "2025-08-04",
      "open": 566.98,
      "high": 577.21,
      "low": 562.01,
      "close": 571.54
    },
    {
      "date": "2025-08-05",
      "open": 570.25,
      "high": 579.82,
      "low": 568.5,
      "close": 569.9
    },
    {
      "date": "2025-08-06",
      "open": 569.0,
      "high": 573.465,
      "low": 550.495,
      "close": 555.13
    },
    {
      "date": "2025-08-07",
      "open": 557.66,
      "high": 565.48,
      "low": 553.05,
      "close": 559.8
    },
    {
      "date": "2025-08-08",
      "open": 559.8,
      "high": 567.69,
      "low": 558.0618,
      "close": 563.0
    },
    {
      "date": "2025-08-11",
      "open": 561.52,
      "high": 572.5799,
      "low": 544.16,
      "close": 545.94
    },
    {
      "date": "2025-08-12",
      "open": 547.94,
      "high": 562.7434,
      "low": 547.085,
      "close": 556.555
    },
    {
      "date": "2025-08-13",
      "open": 557.08,
      "high": 565.5,
      "low": 552.0,
      "close": 561.55
    },
    {
      "date": "2025-08-14",
      "open": 560.9,
      "high": 573.486,
      "low": 558.0,
      "close": 565.97
    },
    {
      "date": "2025-08-15",
      "open": 577.96,
      "high": 581.95,
      "low": 570.84,
      "close": 580.41
    },
    {
      "date": "2025-08-18",
      "open": 582.09,
      "high": 585.0,
      "low": 573.81,
      "close": 573.91
    },
    {
      "date": "2025-08-19",
      "open": 575.3,
      "high": 581.6885,
      "low": 570.8,
      "close": 571.78
    },
    {
      "date": "2025-08-20",
      "open": 572.33,
      "high": 596.9224,
      "low": 570.39,
      "close": 591.01
    },
    {
      "date": "2025-08-21",
      "open": 586.87,
      "high": 605.18,
      "low": 585.1034,
      "close": 598.16
    },
    {
      "date": "2025-08-22",
      "open": 602.35,
      "high": 610.45,
      "low": 585.5,
      "close": 589.48
    },
    {
      "date": "2025-08-25",
      "open": 591.06,
      "high": 594.88,
      "low": 572.25,
      "close": 572.38
    },
    {
      "date": "2025-08-26",
      "open": 573.0,
      "high": 588.1,
      "low": 567.08,
      "close": 587.65
    },
    {
      "date": "2025-08-27",
      "open": 591.87,
      "high": 597.02,
      "low": 585.5,
      "close": 586.96
    },
    {
      "date": "2025-08-28",
      "open": 586.43,
      "high": 590.955,
      "low": 575.04,
      "close": 579.61
    },
    {
      "date": "2025-08-29",
      "open": 577.15,
      "high": 581.245,
      "low": 575.8871,
      "close": 580.7
    },
    {
      "date": "2025-09-02",
      "open": 580.54,
      "high": 585.49,
      "low": 570.35,
      "close": 577.9
    },
    {
      "date": "2025-09-03",
      "open": 581.99,
      "high": 588.6999,
      "low": 562.785,
      "close": 563.8
    },
    {
      "date": "2025-09-04",
      "open": 568.01,
      "high": 581.98,
      "low": 559.62,
      "close": 567.22
    },
    {
      "date": "2025-09-05",
      "open": 565.15,
      "high": 577.75,
      "low": 565.0,
      "close": 573.38
    },
    {
      "date": "2025-09-08",
      "open": 571.2,
      "high": 571.2,
      "low": 552.81,
      "close": 558.44
    },
    {
      "date": "2025-09-09",
      "open": 557.0,
      "high": 563.565,
      "low": 554.8,
      "close": 556.53
    },
    {
      "date": "2025-09-10",
      "open": 555.21,
      "high": 560.0,
      "low": 552.98,
      "close": 555.83
    },
    {
      "date": "2025-09-11",
      "open": 555.81,
      "high": 570.76,
      "low": 555.81,
      "close": 568.2
    },
    {
      "date": "2025-09-12",
      "open": 567.34,
      "high": 570.0,
      "low": 559.45,
      "close": 560.0
    },
    {
      "date": "2025-09-15",
      "open": 558.54,
      "high": 573.69,
      "low": 558.54,
      "close": 572.59
    },
    {
      "date": "2025-09-16",
      "open": 573.43,
      "high": 579.4,
      "low": 567.305,
      "close": 575.06
    },
    {
      "date": "2025-09-17",
      "open": 576.31,
      "high": 587.67,
      "low": 576.31,
      "close": 585.5
    },
    {
      "date": "2025-09-18",
      "open": 589.52,
      "high": 600.0,
      "low": 583.92,
      "close": 598.71
    },
    {
      "date": "2025-09-19",
      "open": 602.54,
      "high": 603.465,
      "low": 591.0,
      "close": 591.99
    },
    {
      "date": "2025-09-22",
      "open": 593.0,
      "high": 600.75,
      "low": 588.6734,
      "close": 595.68
    },
    {
      "date": "2025-09-23",
      "open": 580.0,
      "high": 581.9999,
      "low": 565.45,
      "close": 567.89
    },
    {
      "date": "2025-09-24",
      "open": 567.89,
      "high": 577.98,
      "low": 566.0,
      "close": 576.98
    },
    {
      "date": "2025-09-25",
      "open": 577.3,
      "high": 579.0,
      "low": 549.2,
      "close": 555.51
    },
    {
      "date": "2025-09-26",
      "open": 562.0,
      "high": 564.61,
      "low": 550.7101,
      "close": 563.9
    },
    {
      "date": "2025-09-29",
      "open": 563.9,
      "high": 564.91,
      "low": 557.34,
      "close": 560.75
    },
    {
      "date": "2025-09-30",
      "open": 560.58,
      "high": 574.04,
      "low": 555.0001,
      "close": 562.27
    },
    {
      "date": "2025-10-01",
      "open": 570.87,
      "high": 615.39,
      "low": 569.99,
      "close": 599.94
    },
    {
      "date": "2025-10-02",
      "open": 600.42,
      "high": 605.4125,
      "low": 596.6,
      "close": 600.0
    },
    {
      "date": "2025-10-03",
      "open": 602.09,
      "high": 618.01,
      "low": 599.87,
      "close": 600.0
    },
    {
      "date": "2025-10-06",
      "open": 602.0,
      "high": 603.65,
      "low": 584.4063,
      "close": 585.48
    },
    {
      "date": "2025-10-07",
      "open": 587.59,
      "high": 591.4499,
      "low": 578.42,
      "close": 583.24
    },
    {
      "date": "2025-10-08",
      "open": 584.01,
      "high": 605.0,
      "low": 560.97,
      "close": 563.86
    },
    {
      "date": "2025-10-09",
      "open": 569.02,
      "high": 574.72,
      "low": 563.51,
      "close": 569.9
    },
    {
      "date": "2025-10-10",
      "open": 569.29,
      "high": 577.17,
      "low": 555.545,
      "close": 564.63
    },
    {
      "date": "2025-10-13",
      "open": 551.5,
      "high": 563.77,
      "low": 541.0,
      "close": 557.73
    },
    {
      "date": "2025-10-14",
      "open": 556.92,
      "high": 576.18,
      "low": 553.865,
      "close": 572.6
    },
    {
      "date": "2025-10-15",
      "open": 575.03,
      "high": 584.865,
      "low": 569.02,
      "close": 576.42
    },
    {
      "date": "2025-10-16",
      "open": 583.01,
      "high": 589.08,
      "low": 564.0,
      "close": 569.17
    },
    {
      "date": "2025-10-17",
      "open": 570.35,
      "high": 579.045,
      "low": 566.11,
      "close": 578.05
    },
    {
      "date": "2025-10-20",
      "open": 579.41,
      "high": 582.645,
      "low": 574.23,
      "close": 576.77
    },
    {
      "date": "2025-10-21",
      "open": 574.6,
      "high": 582.405,
      "low": 572.82,
      "close": 579.34
    },
    {
      "date": "2025-10-22",
      "open": 580.21,
      "high": 588.705,
      "low": 578.6,
      "close": 584.74
    },
    {
      "date": "2025-10-23",
      "open": 579.68,
      "high": 584.001,
      "low": 572.7454,
      "close": 575.69
    },
    {
      "date": "2025-10-24",
      "open": 579.65,
      "high": 582.7,
      "low": 576.2,
      "close": 577.95
    },
    {
      "date": "2025-10-27",
      "open": 580.5,
      "high": 586.145,
      "low": 575.93,
      "close": 585.31
    },
    {
      "date": "2025-10-28",
      "open": 612.02,
      "high": 655.7,
      "low": 605.03,
      "close": 654.48
    },
    {
      "date": "2025-10-29",
      "open": 650.41,
      "high": 659.98,
      "low": 637.66,
      "close": 652.91
    },
    {
      "date": "2025-10-30",
      "open": 645.56,
      "high": 664.0,
      "low": 643.915,
      "close": 654.04
    },
    {
      "date": "2025-10-31",
      "open": 649.45,
      "high": 660.0,
      "low": 645.0,
      "close": 651.8
    },
    {
      "date": "2025-11-03",
      "open": 657.46,
      "high": 657.46,
      "low": 627.5,
      "close": 642.25
    },
    {
      "date": "2025-11-04",
      "open": 643.78,
      "high": 646.2213,
      "low": 625.14,
      "close": 628.0
    },
    {
      "date": "2025-11-05",
      "open": 631.1,
      "high": 646.8949,
      "low": 628.0001,
      "close": 644.19
    },
    {
      "date": "2025-11-06",
      "open": 640.83,
      "high": 657.0,
      "low": 640.83,
      "close": 646.87
    },
    {
      "date": "2025-11-07",
      "open": 650.35,
      "high": 658.21,
      "low": 640.9901,
      "close": 657.53
    },
    {
      "date": "2025-11-10",
      "open": 656.0,
      "high": 665.99,
      "low": 653.19,
      "close": 654.74
    },
    {
      "date": "2025-11-11",
      "open": 651.48,
      "high": 676.33,
      "low": 651.38,
      "close": 674.55
    },
    {
      "date": "2025-11-12",
      "open": 678.89,
      "high": 690.78,
      "low": 672.67,
      "close": 681.72
    },
    {
      "date": "2025-11-13",
      "open": 683.0,
      "high": 713.58,
      "low": 679.93,
      "close": 694.99
    },
    {
      "date": "2025-11-14",
      "open": 697.19,
      "high": 699.27,
      "low": 685.95,
      "close": 693.5
    },
    {
      "date": "2025-11-17",
      "open": 693.34,
      "high": 711.88,
      "low": 692.29,
      "close": 704.31
    },
    {
      "date": "2025-11-18",
      "open": 702.51,
      "high": 727.97,
      "low": 699.22,
      "close": 725.34
    },
    {
      "date": "2025-11-19",
      "open": 727.81,
      "high": 727.81,
      "low": 702.6301,
      "close": 702.75
    },
    {
      "date": "2025-11-20",
      "open": 725.0,
      "high": 753.51,
      "low": 720.02,
      "close": 737.0
    },
    {
      "date": "2025-11-21",
      "open": 736.01,
      "high": 764.09,
      "low": 735.735,
      "close": 755.9
    },
    {
      "date": "2025-11-24",
      "open": 759.05,
      "high": 773.13,
      "low": 756.64,
      "close": 761.45
    },
    {
      "date": "2025-11-25",
      "open": 764.88,
      "high": 790.57,
      "low": 760.005,
      "close": 787.32
    },
    {
      "date": "2025-11-26",
      "open": 785.72,
      "high": 790.98,
      "low": 777.0,
      "close": 784.61
    },
    {
      "date": "2025-11-28",
      "open": 784.7,
      "high": 788.98,
      "low": 779.5,
      "close": 780.19
    }
  ],
  "markers": [
    {
      "date": "2025-11-03",
      "type": "buy",
      "price": 657.46
    }
  ]
}