{
  "ticker": "VSCO",
  "name": "VSCO",
  "sector": "Unknown",
  "description": "Investment Thesis available in report.",
  "history": [
    {
      "date": "2024-12-02",
      "open": 39.13,
      "high": 42.95,
      "low": 38.76,
      "close": 41.92
    },
    {
      "date": "2024-12-03",
      "open": 41.77,
      "high": 42.73,
      "low": 40.9342,
      "close": 41.9
    },
    {
      "date": "2024-12-04",
      "open": 41.6,
      "high": 43.92,
      "low": 41.3,
      "close": 43.9
    },
    {
      "date": "2024-12-05",
      "open": 42.81,
      "high": 44.4,
      "low": 42.425,
      "close": 43.02
    },
    {
      "date": "2024-12-06",
      "open": 45.825,
      "high": 48.7,
      "low": 44.5,
      "close": 48.02
    },
    {
      "date": "2024-12-09",
      "open": 48.0,
      "high": 48.688,
      "low": 45.93,
      "close": 47.2
    },
    {
      "date": "2024-12-10",
      "open": 48.38,
      "high": 48.38,
      "low": 44.765,
      "close": 46.63
    },
    {
      "date": "2024-12-11",
      "open": 46.78,
      "high": 47.6,
      "low": 45.95,
      "close": 47.25
    },
    {
      "date": "2024-12-12",
      "open": 46.77,
      "high": 47.2499,
      "low": 45.5,
      "close": 46.79
    },
    {
      "date": "2024-12-13",
      "open": 46.94,
      "high": 48.73,
      "low": 46.43,
      "close": 48.71
    },
    {
      "date": "2024-12-16",
      "open": 47.82,
      "high": 48.72,
      "low": 45.55,
      "close": 45.89
    },
    {
      "date": "2024-12-17",
      "open": 45.83,
      "high": 46.22,
      "low": 44.42,
      "close": 44.75
    },
    {
      "date": "2024-12-18",
      "open": 45.46,
      "high": 45.72,
      "low": 43.14,
      "close": 43.35
    },
    {
      "date": "2024-12-19",
      "open": 44.0,
      "high": 44.64,
      "low": 42.21,
      "close": 42.42
    },
    {
      "date": "2024-12-20",
      "open": 42.0,
      "high": 45.89,
      "low": 41.855,
      "close": 44.96
    },
    {
      "date": "2024-12-23",
      "open": 44.3,
      "high": 44.725,
      "low": 42.0,
      "close": 42.18
    },
    {
      "date": "2024-12-24",
      "open": 42.2,
      "high": 42.76,
      "low": 40.68,
      "close": 41.64
    },
    {
      "date": "2024-12-26",
      "open": 42.11,
      "high": 42.23,
      "low": 41.1,
      "close": 41.76
    },
    {
      "date": "2024-12-27",
      "open": 41.63,
      "high": 42.72,
      "low": 41.37,
      "close": 42.26
    },
    {
      "date": "2024-12-30",
      "open": 41.65,
      "high": 42.875,
      "low": 41.15,
      "close": 41.89
    },
    {
      "date": "2024-12-31",
      "open": 41.98,
      "high": 42.3,
      "low": 40.85,
      "close": 41.42
    },
    {
      "date": "2025-01-02",
      "open": 41.58,
      "high": 42.16,
      "low": 40.05,
      "close": 40.42
    },
    {
      "date": "2025-01-03",
      "open": 40.45,
      "high": 42.0,
      "low": 40.125,
      "close": 41.86
    },
    {
      "date": "2025-01-06",
      "open": 42.15,
      "high": 42.27,
      "low": 38.92,
      "close": 39.72
    },
    {
      "date": "2025-01-07",
      "open": 39.985,
      "high": 41.35,
      "low": 39.06,
      "close": 39.14
    },
    {
      "date": "2025-01-08",
      "open": 39.12,
      "high": 39.26,
      "low": 38.34,
      "close": 38.49
    },
    {
      "date": "2025-01-10",
      "open": 37.98,
      "high": 38.38,
      "low": 37.47,
      "close": 37.58
    },
    {
      "date": "2025-01-13",
      "open": 37.2,
      "high": 37.495,
      "low": 34.52,
      "close": 35.82
    },
    {
      "date": "2025-01-14",
      "open": 36.54,
      "high": 38.0,
      "low": 35.29,
      "close": 35.48
    },
    {
      "date": "2025-01-15",
      "open": 36.61,
      "high": 36.9569,
      "low": 35.42,
      "close": 36.23
    },
    {
      "date": "2025-01-16",
      "open": 36.47,
      "high": 37.335,
      "low": 35.51,
      "close": 36.37
    },
    {
      "date": "2025-01-17",
      "open": 36.75,
      "high": 37.629,
      "low": 35.77,
      "close": 37.1
    },
    {
      "date": "2025-01-21",
      "open": 37.18,
      "high": 39.0,
      "low": 37.0,
      "close": 38.74
    },
    {
      "date": "2025-01-22",
      "open": 38.66,
      "high": 39.54,
      "low": 37.81,
      "close": 38.6
    },
    {
      "date": "2025-01-23",
      "open": 38.04,
      "high": 38.54,
      "low": 37.77,
      "close": 38.33
    },
    {
      "date": "2025-01-24",
      "open": 39.75,
      "high": 40.25,
      "low": 37.59,
      "close": 37.75
    },
    {
      "date": "2025-01-27",
      "open": 37.69,
      "high": 37.69,
      "low": 36.8824,
      "close": 37.34
    },
    {
      "date": "2025-01-28",
      "open": 38.62,
      "high": 39.66,
      "low": 37.64,
      "close": 37.9
    },
    {
      "date": "2025-01-29",
      "open": 33.75,
      "high": 36.4995,
      "low": 33.65,
      "close": 36.16
    },
    {
      "date": "2025-01-30",
      "open": 36.38,
      "high": 37.12,
      "low": 35.89,
      "close": 36.78
    },
    {
      "date": "2025-01-31",
      "open": 36.74,
      "high": 37.09,
      "low": 35.87,
      "close": 36.36
    },
    {
      "date": "2025-02-03",
      "open": 35.02,
      "high": 36.22,
      "low": 34.5318,
      "close": 34.91
    },
    {
      "date": "2025-02-04",
      "open": 34.76,
      "high": 34.76,
      "low": 33.65,
      "close": 34.13
    },
    {
      "date": "2025-02-05",
      "open": 34.0,
      "high": 34.57,
      "low": 33.83,
      "close": 34.1
    },
    {
      "date": "2025-02-06",
      "open": 34.8,
      "high": 35.24,
      "low": 33.52,
      "close": 33.66
    },
    {
      "date": "2025-02-07",
      "open": 33.48,
      "high": 33.61,
      "low": 32.05,
      "close": 32.14
    },
    {
      "date": "2025-02-10",
      "open": 32.33,
      "high": 33.59,
      "low": 32.12,
      "close": 32.8
    },
    {
      "date": "2025-02-11",
      "open": 32.49,
      "high": 33.0,
      "low": 32.1,
      "close": 32.63
    },
    {
      "date": "2025-02-12",
      "open": 32.13,
      "high": 32.67,
      "low": 31.65,
      "close": 32.6
    },
    {
      "date": "2025-02-13",
      "open": 32.99,
      "high": 33.2085,
      "low": 32.1991,
      "close": 32.48
    },
    {
      "date": "2025-02-14",
      "open": 32.73,
      "high": 33.22,
      "low": 31.82,
      "close": 32.83
    },
    {
      "date": "2025-02-18",
      "open": 32.78,
      "high": 32.865,
      "low": 30.86,
      "close": 31.24
    },
    {
      "date": "2025-02-19",
      "open": 31.07,
      "high": 31.1,
      "low": 29.46,
      "close": 30.03
    },
    {
      "date": "2025-02-20",
      "open": 29.97,
      "high": 30.26,
      "low": 28.93,
      "close": 29.33
    },
    {
      "date": "2025-02-21",
      "open": 29.99,
      "high": 30.48,
      "low": 27.67,
      "close": 27.96
    },
    {
      "date": "2025-02-24",
      "open": 28.15,
      "high": 29.3,
      "low": 27.52,
      "close": 28.61
    },
    {
      "date": "2025-02-25",
      "open": 29.26,
      "high": 30.0,
      "low": 28.3,
      "close": 28.45
    },
    {
      "date": "2025-02-26",
      "open": 29.02,
      "high": 29.34,
      "low": 28.03,
      "close": 28.35
    },
    {
      "date": "2025-02-27",
      "open": 28.2,
      "high": 28.481,
      "low": 26.73,
      "close": 26.87
    },
    {
      "date": "2025-02-28",
      "open": 26.59,
      "high": 27.17,
      "low": 25.99,
      "close": 26.73
    },
    {
      "date": "2025-03-03",
      "open": 26.78,
      "high": 27.47,
      "low": 23.915,
      "close": 24.01
    },
    {
      "date": "2025-03-04",
      "open": 23.51,
      "high": 23.62,
      "low": 22.46,
      "close": 23.38
    },
    {
      "date": "2025-03-05",
      "open": 23.08,
      "high": 23.24,
      "low": 21.2,
      "close": 22.21
    },
    {
      "date": "2025-03-06",
      "open": 20.86,
      "high": 21.67,
      "low": 19.34,
      "close": 20.38
    },
    {
      "date": "2025-03-07",
      "open": 20.01,
      "high": 20.17,
      "low": 18.4,
      "close": 19.05
    },
    {
      "date": "2025-03-10",
      "open": 18.37,
      "high": 18.58,
      "low": 16.66,
      "close": 16.78
    },
    {
      "date": "2025-03-11",
      "open": 17.04,
      "high": 17.5,
      "low": 16.16,
      "close": 16.25
    },
    {
      "date": "2025-03-12",
      "open": 16.7,
      "high": 17.83,
      "low": 16.62,
      "close": 17.18
    },
    {
      "date": "2025-03-13",
      "open": 17.85,
      "high": 18.06,
      "low": 16.93,
      "close": 17.65
    },
    {
      "date": "2025-03-14",
      "open": 18.08,
      "high": 18.97,
      "low": 18.0,
      "close": 18.57
    },
    {
      "date": "2025-03-17",
      "open": 18.9,
      "high": 20.4386,
      "low": 18.83,
      "close": 20.06
    },
    {
      "date": "2025-03-18",
      "open": 19.75,
      "high": 20.475,
      "low": 19.1607,
      "close": 20.39
    },
    {
      "date": "2025-03-19",
      "open": 20.45,
      "high": 21.81,
      "low": 20.45,
      "close": 21.68
    },
    {
      "date": "2025-03-20",
      "open": 21.47,
      "high": 22.72,
      "low": 21.33,
      "close": 21.75
    },
    {
      "date": "2025-03-21",
      "open": 20.9,
      "high": 21.49,
      "low": 20.42,
      "close": 20.92
    },
    {
      "date": "2025-03-24",
      "open": 21.38,
      "high": 21.6246,
      "low": 20.76,
      "close": 21.38
    },
    {
      "date": "2025-03-25",
      "open": 21.11,
      "high": 21.17,
      "low": 20.4316,
      "close": 20.57
    },
    {
      "date": "2025-03-26",
      "open": 20.45,
      "high": 20.565,
      "low": 19.3,
      "close": 19.55
    },
    {
      "date": "2025-03-27",
      "open": 19.24,
      "high": 19.89,
      "low": 19.16,
      "close": 19.5
    },
    {
      "date": "2025-03-28",
      "open": 19.39,
      "high": 19.76,
      "low": 18.1,
      "close": 18.32
    },
    {
      "date": "2025-03-31",
      "open": 17.8,
      "high": 18.61,
      "low": 17.62,
      "close": 18.58
    },
    {
      "date": "2025-04-01",
      "open": 18.5,
      "high": 19.0,
      "low": 17.92,
      "close": 18.37
    },
    {
      "date": "2025-04-02",
      "open": 18.21,
      "high": 19.43,
      "low": 18.09,
      "close": 19.22
    },
    {
      "date": "2025-04-03",
      "open": 17.185,
      "high": 18.0,
      "low": 14.6,
      "close": 14.87
    },
    {
      "date": "2025-04-04",
      "open": 14.28,
      "high": 17.45,
      "low": 13.76,
      "close": 16.95
    },
    {
      "date": "2025-04-07",
      "open": 16.04,
      "high": 17.87,
      "low": 15.79,
      "close": 17.21
    },
    {
      "date": "2025-04-08",
      "open": 18.05,
      "high": 18.13,
      "low": 15.96,
      "close": 16.81
    },
    {
      "date": "2025-04-09",
      "open": 16.75,
      "high": 20.68,
      "low": 16.42,
      "close": 19.98
    },
    {
      "date": "2025-04-10",
      "open": 19.25,
      "high": 19.355,
      "low": 17.175,
      "close": 17.59
    },
    {
      "date": "2025-04-11",
      "open": 17.41,
      "high": 17.85,
      "low": 16.625,
      "close": 17.09
    },
    {
      "date": "2025-04-14",
      "open": 17.72,
      "high": 18.15,
      "low": 16.2,
      "close": 16.28
    },
    {
      "date": "2025-04-15",
      "open": 15.95,
      "high": 16.6992,
      "low": 15.54,
      "close": 15.93
    },
    {
      "date": "2025-04-16",
      "open": 15.79,
      "high": 16.16,
      "low": 15.38,
      "close": 15.62
    },
    {
      "date": "2025-04-17",
      "open": 15.63,
      "high": 16.22,
      "low": 15.34,
      "close": 16.0
    },
    {
      "date": "2025-04-21",
      "open": 15.84,
      "high": 16.51,
      "low": 15.51,
      "close": 16.37
    },
    {
      "date": "2025-04-22",
      "open": 16.61,
      "high": 17.975,
      "low": 16.595,
      "close": 17.3
    },
    {
      "date": "2025-04-23",
      "open": 18.27,
      "high": 18.62,
      "low": 17.725,
      "close": 18.07
    },
    {
      "date": "2025-04-24",
      "open": 17.9,
      "high": 18.73,
      "low": 17.805,
      "close": 18.57
    },
    {
      "date": "2025-04-25",
      "open": 18.14,
      "high": 18.74,
      "low": 18.02,
      "close": 18.54
    },
    {
      "date": "2025-04-28",
      "open": 18.54,
      "high": 19.055,
      "low": 18.255,
      "close": 18.96
    },
    {
      "date": "2025-04-29",
      "open": 18.89,
      "high": 19.16,
      "low": 18.3,
      "close": 18.78
    },
    {
      "date": "2025-04-30",
      "open": 17.655,
      "high": 18.99,
      "low": 17.5,
      "close": 18.8
    },
    {
      "date": "2025-05-01",
      "open": 19.0,
      "high": 19.69,
      "low": 18.91,
      "close": 19.19
    },
    {
      "date": "2025-05-02",
      "open": 19.59,
      "high": 20.06,
      "low": 19.365,
      "close": 19.59
    },
    {
      "date": "2025-05-05",
      "open": 19.31,
      "high": 19.8,
      "low": 19.0,
      "close": 19.26
    },
    {
      "date": "2025-05-06",
      "open": 18.94,
      "high": 19.44,
      "low": 18.5901,
      "close": 19.01
    },
    {
      "date": "2025-05-07",
      "open": 19.25,
      "high": 19.58,
      "low": 18.87,
      "close": 19.24
    },
    {
      "date": "2025-05-08",
      "open": 19.84,
      "high": 20.3,
      "low": 19.445,
      "close": 19.74
    },
    {
      "date": "2025-05-09",
      "open": 19.74,
      "high": 19.8735,
      "low": 19.22,
      "close": 19.26
    },
    {
      "date": "2025-05-12",
      "open": 20.995,
      "high": 22.47,
      "low": 20.78,
      "close": 21.92
    },
    {
      "date": "2025-05-13",
      "open": 22.13,
      "high": 22.8399,
      "low": 21.975,
      "close": 22.74
    },
    {
      "date": "2025-05-14",
      "open": 22.42,
      "high": 23.42,
      "low": 22.41,
      "close": 22.78
    },
    {
      "date": "2025-05-15",
      "open": 22.78,
      "high": 23.23,
      "low": 22.3,
      "close": 23.2
    },
    {
      "date": "2025-05-16",
      "open": 23.2,
      "high": 23.735,
      "low": 22.88,
      "close": 23.57
    },
    {
      "date": "2025-05-19",
      "open": 22.77,
      "high": 23.22,
      "low": 22.03,
      "close": 22.79
    },
    {
      "date": "2025-05-20",
      "open": 23.41,
      "high": 23.82,
      "low": 22.71,
      "close": 23.53
    },
    {
      "date": "2025-05-21",
      "open": 22.64,
      "high": 23.06,
      "low": 22.2,
      "close": 22.24
    },
    {
      "date": "2025-05-22",
      "open": 22.21,
      "high": 22.99,
      "low": 22.06,
      "close": 22.85
    },
    {
      "date": "2025-05-23",
      "open": 21.73,
      "high": 22.52,
      "low": 21.68,
      "close": 22.27
    },
    {
      "date": "2025-05-27",
      "open": 22.69,
      "high": 22.8,
      "low": 21.85,
      "close": 22.54
    },
    {
      "date": "2025-05-28",
      "open": 22.06,
      "high": 22.23,
      "low": 20.2101,
      "close": 20.99
    },
    {
      "date": "2025-05-29",
      "open": 21.11,
      "high": 21.11,
      "low": 19.9511,
      "close": 20.71
    },
    {
      "date": "2025-05-30",
      "open": 20.42,
      "high": 21.57,
      "low": 20.21,
      "close": 21.21
    },
    {
      "date": "2025-06-02",
      "open": 21.08,
      "high": 21.44,
      "low": 20.68,
      "close": 20.83
    },
    {
      "date": "2025-06-03",
      "open": 20.64,
      "high": 21.52,
      "low": 20.03,
      "close": 20.27
    },
    {
      "date": "2025-06-04",
      "open": 20.4,
      "high": 20.595,
      "low": 19.68,
      "close": 20.47
    },
    {
      "date": "2025-06-05",
      "open": 20.72,
      "high": 21.3623,
      "low": 20.27,
      "close": 20.88
    },
    {
      "date": "2025-06-06",
      "open": 21.28,
      "high": 22.16,
      "low": 20.97,
      "close": 22.16
    },
    {
      "date": "2025-06-09",
      "open": 22.5,
      "high": 23.3299,
      "low": 22.5,
      "close": 22.72
    },
    {
      "date": "2025-06-10",
      "open": 23.12,
      "high": 23.25,
      "low": 21.95,
      "close": 22.2
    },
    {
      "date": "2025-06-11",
      "open": 22.1,
      "high": 22.4,
      "low": 20.73,
      "close": 21.0
    },
    {
      "date": "2025-06-12",
      "open": 20.56,
      "high": 20.78,
      "low": 19.66,
      "close": 19.81
    },
    {
      "date": "2025-06-13",
      "open": 19.13,
      "high": 19.3462,
      "low": 18.0,
      "close": 18.19
    },
    {
      "date": "2025-06-16",
      "open": 19.225,
      "high": 19.225,
      "low": 18.44,
      "close": 18.62
    },
    {
      "date": "2025-06-17",
      "open": 18.475,
      "high": 18.98,
      "low": 18.355,
      "close": 18.38
    },
    {
      "date": "2025-06-18",
      "open": 18.29,
      "high": 18.87,
      "low": 18.25,
      "close": 18.4
    },
    {
      "date": "2025-06-20",
      "open": 18.69,
      "high": 19.035,
      "low": 18.445,
      "close": 18.83
    },
    {
      "date": "2025-06-23",
      "open": 18.57,
      "high": 18.92,
      "low": 18.31,
      "close": 18.58
    },
    {
      "date": "2025-06-24",
      "open": 18.95,
      "high": 19.73,
      "low": 18.63,
      "close": 19.5
    },
    {
      "date": "2025-06-25",
      "open": 19.52,
      "high": 19.708,
      "low": 18.671,
      "close": 18.88
    },
    {
      "date": "2025-06-26",
      "open": 19.07,
      "high": 19.145,
      "low": 18.49,
      "close": 18.91
    },
    {
      "date": "2025-06-27",
      "open": 19.3,
      "high": 19.72,
      "low": 19.04,
      "close": 19.32
    },
    {
      "date": "2025-06-30",
      "open": 19.47,
      "high": 19.57,
      "low": 18.505,
      "close": 18.52
    },
    {
      "date": "2025-07-01",
      "open": 18.49,
      "high": 20.61,
      "low": 18.4,
      "close": 19.54
    },
    {
      "date": "2025-07-02",
      "open": 19.76,
      "high": 20.46,
      "low": 19.08,
      "close": 20.4
    },
    {
      "date": "2025-07-03",
      "open": 20.32,
      "high": 21.14,
      "low": 20.32,
      "close": 20.57
    },
    {
      "date": "2025-07-07",
      "open": 20.59,
      "high": 21.15,
      "low": 20.2,
      "close": 20.46
    },
    {
      "date": "2025-07-08",
      "open": 20.59,
      "high": 20.63,
      "low": 19.57,
      "close": 19.98
    },
    {
      "date": "2025-07-09",
      "open": 20.0,
      "high": 20.2,
      "low": 19.65,
      "close": 19.99
    },
    {
      "date": "2025-07-10",
      "open": 19.83,
      "high": 20.62,
      "low": 19.55,
      "close": 20.14
    },
    {
      "date": "2025-07-11",
      "open": 19.97,
      "high": 19.985,
      "low": 19.12,
      "close": 19.14
    },
    {
      "date": "2025-07-14",
      "open": 19.04,
      "high": 19.07,
      "low": 18.54,
      "close": 18.95
    },
    {
      "date": "2025-07-15",
      "open": 19.05,
      "high": 19.17,
      "low": 17.99,
      "close": 18.27
    },
    {
      "date": "2025-07-16",
      "open": 18.38,
      "high": 18.57,
      "low": 17.53,
      "close": 17.7
    },
    {
      "date": "2025-07-17",
      "open": 17.9,
      "high": 18.58,
      "low": 17.78,
      "close": 18.38
    },
    {
      "date": "2025-07-18",
      "open": 18.89,
      "high": 19.23,
      "low": 18.65,
      "close": 19.04
    },
    {
      "date": "2025-07-21",
      "open": 19.42,
      "high": 20.2,
      "low": 19.2282,
      "close": 19.92
    },
    {
      "date": "2025-07-22",
      "open": 19.995,
      "high": 21.44,
      "low": 19.995,
      "close": 21.14
    },
    {
      "date": "2025-07-23",
      "open": 21.5,
      "high": 22.2,
      "low": 21.31,
      "close": 21.63
    },
    {
      "date": "2025-07-24",
      "open": 21.35,
      "high": 21.5,
      "low": 20.75,
      "close": 20.81
    },
    {
      "date": "2025-07-25",
      "open": 20.82,
      "high": 21.48,
      "low": 20.5,
      "close": 21.48
    },
    {
      "date": "2025-07-28",
      "open": 21.75,
      "high": 21.75,
      "low": 20.47,
      "close": 20.8
    },
    {
      "date": "2025-07-29",
      "open": 20.68,
      "high": 20.98,
      "low": 19.71,
      "close": 19.92
    },
    {
      "date": "2025-07-30",
      "open": 20.04,
      "high": 20.105,
      "low": 19.27,
      "close": 19.52
    },
    {
      "date": "2025-07-31",
      "open": 19.31,
      "high": 19.5024,
      "low": 18.41,
      "close": 18.8
    },
    {
      "date": "2025-08-01",
      "open": 18.4,
      "high": 18.86,
      "low": 18.04,
      "close": 18.72
    },
    {
      "date": "2025-08-04",
      "open": 18.93,
      "high": 20.66,
      "low": 18.93,
      "close": 20.56
    },
    {
      "date": "2025-08-05",
      "open": 20.61,
      "high": 20.61,
      "low": 19.18,
      "close": 19.71
    },
    {
      "date": "2025-08-06",
      "open": 19.72,
      "high": 20.59,
      "low": 19.15,
      "close": 20.48
    },
    {
      "date": "2025-08-07",
      "open": 21.0,
      "high": 21.9,
      "low": 20.88,
      "close": 21.68
    },
    {
      "date": "2025-08-08",
      "open": 21.51,
      "high": 21.59,
      "low": 20.945,
      "close": 21.12
    },
    {
      "date": "2025-08-11",
      "open": 21.2,
      "high": 21.46,
      "low": 20.475,
      "close": 21.32
    },
    {
      "date": "2025-08-12",
      "open": 21.53,
      "high": 22.39,
      "low": 21.42,
      "close": 22.2
    },
    {
      "date": "2025-08-13",
      "open": 22.08,
      "high": 22.81,
      "low": 21.54,
      "close": 22.63
    },
    {
      "date": "2025-08-14",
      "open": 21.88,
      "high": 22.65,
      "low": 21.47,
      "close": 22.42
    },
    {
      "date": "2025-08-15",
      "open": 22.36,
      "high": 22.85,
      "low": 22.2345,
      "close": 22.34
    },
    {
      "date": "2025-08-18",
      "open": 22.3,
      "high": 22.84,
      "low": 22.078,
      "close": 22.72
    },
    {
      "date": "2025-08-19",
      "open": 22.92,
      "high": 23.26,
      "low": 22.0925,
      "close": 22.38
    },
    {
      "date": "2025-08-20",
      "open": 21.99,
      "high": 22.5,
      "low": 21.68,
      "close": 22.01
    },
    {
      "date": "2025-08-21",
      "open": 21.5,
      "high": 21.84,
      "low": 21.2296,
      "close": 21.34
    },
    {
      "date": "2025-08-22",
      "open": 21.58,
      "high": 22.62,
      "low": 21.58,
      "close": 22.15
    },
    {
      "date": "2025-08-25",
      "open": 21.91,
      "high": 22.36,
      "low": 21.64,
      "close": 21.76
    },
    {
      "date": "2025-08-26",
      "open": 21.89,
      "high": 22.06,
      "low": 21.39,
      "close": 21.99
    },
    {
      "date": "2025-08-27",
      "open": 22.17,
      "high": 23.03,
      "low": 22.105,
      "close": 22.78
    },
    {
      "date": "2025-08-28",
      "open": 24.99,
      "high": 25.47,
      "low": 21.9112,
      "close": 22.67
    },
    {
      "date": "2025-08-29",
      "open": 23.06,
      "high": 23.46,
      "low": 22.24,
      "close": 23.02
    },
    {
      "date": "2025-09-02",
      "open": 22.7,
      "high": 22.7,
      "low": 22.02,
      "close": 22.4
    },
    {
      "date": "2025-09-03",
      "open": 22.54,
      "high": 24.0,
      "low": 22.54,
      "close": 22.97
    },
    {
      "date": "2025-09-04",
      "open": 23.28,
      "high": 25.7,
      "low": 23.15,
      "close": 25.67
    },
    {
      "date": "2025-09-05",
      "open": 25.86,
      "high": 26.74,
      "low": 25.7,
      "close": 26.25
    },
    {
      "date": "2025-09-08",
      "open": 26.21,
      "high": 26.21,
      "low": 25.19,
      "close": 25.65
    },
    {
      "date": "2025-09-09",
      "open": 25.4,
      "high": 25.71,
      "low": 25.0,
      "close": 25.54
    },
    {
      "date": "2025-09-10",
      "open": 25.3,
      "high": 25.8,
      "low": 25.1649,
      "close": 25.66
    },
    {
      "date": "2025-09-11",
      "open": 26.61,
      "high": 27.1,
      "low": 26.13,
      "close": 27.02
    },
    {
      "date": "2025-09-12",
      "open": 26.9,
      "high": 26.965,
      "low": 25.84,
      "close": 26.44
    },
    {
      "date": "2025-09-15",
      "open": 26.92,
      "high": 28.06,
      "low": 26.7601,
      "close": 27.7
    },
    {
      "date": "2025-09-16",
      "open": 27.34,
      "high": 27.52,
      "low": 26.28,
      "close": 26.29
    },
    {
      "date": "2025-09-17",
      "open": 26.3,
      "high": 27.93,
      "low": 26.25,
      "close": 27.01
    },
    {
      "date": "2025-09-18",
      "open": 27.1,
      "high": 27.71,
      "low": 26.75,
      "close": 27.53
    },
    {
      "date": "2025-09-19",
      "open": 27.52,
      "high": 27.6,
      "low": 26.25,
      "close": 26.62
    },
    {
      "date": "2025-09-22",
      "open": 26.75,
      "high": 26.78,
      "low": 25.3601,
      "close": 25.56
    },
    {
      "date": "2025-09-23",
      "open": 25.81,
      "high": 26.2525,
      "low": 25.305,
      "close": 25.69
    },
    {
      "date": "2025-09-24",
      "open": 25.34,
      "high": 25.995,
      "low": 25.34,
      "close": 25.65
    },
    {
      "date": "2025-09-25",
      "open": 25.32,
      "high": 25.99,
      "low": 25.09,
      "close": 25.59
    },
    {
      "date": "2025-09-26",
      "open": 25.44,
      "high": 26.29,
      "low": 25.44,
      "close": 26.24
    },
    {
      "date": "2025-09-29",
      "open": 26.66,
      "high": 26.69,
      "low": 25.92,
      "close": 26.49
    },
    {
      "date": "2025-09-30",
      "open": 26.44,
      "high": 27.3,
      "low": 26.39,
      "close": 27.14
    },
    {
      "date": "2025-10-01",
      "open": 27.41,
      "high": 29.75,
      "low": 27.25,
      "close": 29.35
    },
    {
      "date": "2025-10-02",
      "open": 29.04,
      "high": 29.9293,
      "low": 28.71,
      "close": 29.18
    },
    {
      "date": "2025-10-03",
      "open": 30.0,
      "high": 30.0,
      "low": 28.9,
      "close": 29.09
    },
    {
      "date": "2025-10-06",
      "open": 29.35,
      "high": 29.74,
      "low": 28.64,
      "close": 29.2
    },
    {
      "date": "2025-10-07",
      "open": 28.92,
      "high": 29.255,
      "low": 28.0411,
      "close": 28.47
    },
    {
      "date": "2025-10-08",
      "open": 28.55,
      "high": 30.27,
      "low": 28.46,
      "close": 30.22
    },
    {
      "date": "2025-10-09",
      "open": 30.3,
      "high": 30.45,
      "low": 29.175,
      "close": 29.59
    },
    {
      "date": "2025-10-10",
      "open": 29.82,
      "high": 30.135,
      "low": 28.19,
      "close": 28.25
    },
    {
      "date": "2025-10-13",
      "open": 28.59,
      "high": 29.48,
      "low": 28.5,
      "close": 29.06
    },
    {
      "date": "2025-10-14",
      "open": 28.54,
      "high": 29.735,
      "low": 28.15,
      "close": 29.46
    },
    {
      "date": "2025-10-15",
      "open": 29.81,
      "high": 31.1514,
      "low": 29.8,
      "close": 30.39
    },
    {
      "date": "2025-10-16",
      "open": 30.34,
      "high": 31.34,
      "low": 29.65,
      "close": 30.19
    },
    {
      "date": "2025-10-17",
      "open": 29.99,
      "high": 31.06,
      "low": 29.67,
      "close": 30.28
    },
    {
      "date": "2025-10-20",
      "open": 30.72,
      "high": 31.65,
      "low": 30.69,
      "close": 31.52
    },
    {
      "date": "2025-10-21",
      "open": 31.42,
      "high": 31.97,
      "low": 30.92,
      "close": 31.37
    },
    {
      "date": "2025-10-22",
      "open": 31.01,
      "high": 31.74,
      "low": 30.6501,
      "close": 31.09
    },
    {
      "date": "2025-10-23",
      "open": 31.13,
      "high": 32.77,
      "low": 30.9,
      "close": 32.74
    },
    {
      "date": "2025-10-24",
      "open": 33.21,
      "high": 34.21,
      "low": 33.1,
      "close": 33.17
    },
    {
      "date": "2025-10-27",
      "open": 34.53,
      "high": 35.08,
      "low": 33.37,
      "close": 34.87
    },
    {
      "date": "2025-10-28",
      "open": 34.92,
      "high": 35.23,
      "low": 34.085,
      "close": 34.53
    },
    {
      "date": "2025-10-29",
      "open": 35.76,
      "high": 38.05,
      "low": 35.5,
      "close": 36.23
    },
    {
      "date": "2025-10-30",
      "open": 35.37,
      "high": 35.58,
      "low": 33.67,
      "close": 33.87
    },
    {
      "date": "2025-10-31",
      "open": 33.84,
      "high": 35.28,
      "low": 33.1989,
      "close": 35.25
    },
    {
      "date": "2025-11-03",
      "open": 35.49,
      "high": 36.645,
      "low": 34.9,
      "close": 36.01
    },
    {
      "date": "2025-11-04",
      "open": 35.13,
      "high": 36.22,
      "low": 34.99,
      "close": 35.37
    },
    {
      "date": "2025-11-05",
      "open": 35.485,
      "high": 39.01,
      "low": 35.056,
      "close": 37.43
    },
    {
      "date": "2025-11-06",
      "open": 37.0,
      "high": 37.38,
      "low": 35.13,
      "close": 36.32
    },
    {
      "date": "2025-11-07",
      "open": 35.34,
      "high": 36.08,
      "low": 34.5,
      "close": 35.07
    },
    {
      "date": "2025-11-10",
      "open": 35.71,
      "high": 35.97,
      "low": 34.0,
      "close": 34.99
    },
    {
      "date": "2025-11-11",
      "open": 35.23,
      "high": 35.43,
      "low": 34.57,
      "close": 34.97
    },
    {
      "date": "2025-11-12",
      "open": 34.99,
      "high": 36.0,
      "low": 34.99,
      "close": 35.39
    },
    {
      "date": "2025-11-13",
      "open": 35.12,
      "high": 36.21,
      "low": 34.67,
      "close": 34.95
    },
    {
      "date": "2025-11-14",
      "open": 34.26,
      "high": 36.33,
      "low": 34.002,
      "close": 35.7
    },
    {
      "date": "2025-11-17",
      "open": 35.67,
      "high": 36.08,
      "low": 34.23,
      "close": 35.09
    },
    {
      "date": "2025-11-18",
      "open": 33.805,
      "high": 34.87,
      "low": 33.61,
      "close": 34.56
    },
    {
      "date": "2025-11-19",
      "open": 34.59,
      "high": 35.4495,
      "low": 34.06,
      "close": 34.79
    },
    {
      "date": "2025-11-20",
      "open": 35.0,
      "high": 36.1,
      "low": 33.695,
      "close": 33.79
    },
    {
      "date": "2025-11-21",
      "open": 33.96,
      "high": 37.095,
      "low": 33.79,
      "close": 36.7
    },
    {
      "date": "2025-11-24",
      "open": 36.64,
      "high": 37.455,
      "low": 35.75,
      "close": 36.67
    },
    {
      "date": "2025-11-25",
      "open": 36.95,
      "high": 39.21,
      "low": 36.55,
      "close": 38.17
    },
    {
      "date": "2025-11-26",
      "open": 38.7,
      "high": 40.8999,
      "low": 38.7,
      "close": 40.19
    },
    {
      "date": "2025-11-28",
      "open": 40.27,
      "high": 41.59,
      "low": 39.71,
      "close": 41.33
    },
    {
      "date": "2025-12-01",
      "open": 40.66,
      "high": 44.38,
      "low": 40.51,
      "close": 44.12
    },
    {
      "date": "2025-12-02",
      "open": 44.05,
      "high": 44.225,
      "low": 41.51,
      "close": 41.97
    },
    {
      "date": "2025-12-03",
      "open": 42.6,
      "high": 43.4999,
      "low": 42.07,
      "close": 42.51
    },
    {
      "date": "2025-12-04",
      "open": 42.05,
      "high": 42.52,
      "low": 40.78,
      "close": 41.57
    },
    {
      "date": "2025-12-05",
      "open": 48.57,
      "high": 50.2199,
      "low": 45.915,
      "close": 49.05
    }
  ],
  "markers": [
    {
      "date": "2025-11-03",
      "type": "buy",
      "price": 35.49
    },
    {
      "date": "2025-12-01",
      "type": "sell",
      "price": 0
    }
  ]
}