{
  "year": 2025,
  "month": 10,
  "chart": [
    {
      "date": "2025-10-01",
      "rel_port": 1.0,
      "rel_spy": 1.0,
      "rel_mag7": 1.0
    },
    {
      "date": "2025-10-02",
      "rel_port": 1.039197190325056,
      "rel_spy": 1.0011519186176976,
      "rel_mag7": 0.9966648648173576
    },
    {
      "date": "2025-10-03",
      "rel_port": 0.9042619608697826,
      "rel_spy": 1.0011369586356496,
      "rel_mag7": 0.989755970881166
    },
    {
      "date": "2025-10-06",
      "rel_port": 0.8957155635468742,
      "rel_spy": 1.0047273543271746,
      "rel_mag7": 1.0030353212031349
    },
    {
      "date": "2025-10-07",
      "rel_port": 0.8187230690295546,
      "rel_spy": 1.0010023187972172,
      "rel_mag7": 0.9914396640280065
    },
    {
      "date": "2025-10-08",
      "rel_port": 0.7721395847238682,
      "rel_spy": 1.006971351634378,
      "rel_mag7": 0.999812192393656
    },
    {
      "date": "2025-10-09",
      "rel_port": 0.6316308646515831,
      "rel_spy": 1.0040541551350137,
      "rel_mag7": 1.0007372266155148
    },
    {
      "date": "2025-10-10",
      "rel_port": 0.7287923573935592,
      "rel_spy": 0.9769167476999027,
      "rel_mag7": 0.96301104162475
    },
    {
      "date": "2025-10-13",
      "rel_port": 0.890688070686845,
      "rel_spy": 0.9919066497120201,
      "rel_mag7": 0.9860205583991615
    },
    {
      "date": "2025-10-14",
      "rel_port": 0.9330568155503794,
      "rel_spy": 0.9906948911661304,
      "rel_mag7": 0.9743976637515819
    },
    {
      "date": "2025-10-15",
      "rel_port": 0.7482439531599763,
      "rel_spy": 0.9950931258882487,
      "rel_mag7": 0.9819522534766776
    },
    {
      "date": "2025-10-16",
      "rel_port": 0.7065250704916028,
      "rel_spy": 0.988316254020495,
      "rel_mag7": 0.9786668242530413
    },
    {
      "date": "2025-10-17",
      "rel_port": 0.7565315407352924,
      "rel_spy": 0.993926247288503,
      "rel_mag7": 0.9879431068508846
    },
    {
      "date": "2025-10-20",
      "rel_port": 0.8206039802214867,
      "rel_spy": 1.004263594883686,
      "rel_mag7": 1.0034212860859293
    },
    {
      "date": "2025-10-21",
      "rel_port": 0.9385621983390772,
      "rel_spy": 1.004248634901638,
      "rel_mag7": 1.0002085903435332
    },
    {
      "date": "2025-10-22",
      "rel_port": 0.9988966531813169,
      "rel_spy": 0.9990276011668784,
      "rel_mag7": 0.9950892845058403
    },
    {
      "date": "2025-10-23",
      "rel_port": 0.9641525796975106,
      "rel_spy": 1.004951754057895,
      "rel_mag7": 1.00347991033066
    },
    {
      "date": "2025-10-24",
      "rel_port": 0.9811999691244508,
      "rel_spy": 1.0131647842022589,
      "rel_mag7": 1.0115485322242361
    },
    {
      "date": "2025-10-27",
      "rel_port": 0.9940280785873532,
      "rel_spy": 1.025117809858628,
      "rel_mag7": 1.037663559152354
    },
    {
      "date": "2025-10-28",
      "rel_port": 1.0219250450646795,
      "rel_spy": 1.027840526591368,
      "rel_mag7": 1.0512858846977713
    },
    {
      "date": "2025-10-29",
      "rel_port": 1.0574160343989942,
      "rel_spy": 1.0283342059989526,
      "rel_mag7": 1.0623817415996153
    },
    {
      "date": "2025-10-30",
      "rel_port": 1.0479422354805463,
      "rel_spy": 1.0170244595706484,
      "rel_mag7": 1.0346711801806474
    },
    {
      "date": "2025-10-31",
      "rel_port": 1.0492850948288,
      "rel_spy": 1.020360535567357,
      "rel_mag7": 1.045896268412419
    }
  ],
  "holdings": [
    {
      "Symbol": "SPHR",
      "Shares": 214.0,
      "CostBasis": 65.99,
      "CurrentPrice": 68.48,
      "UnrealizedPnL": 532.860000000002
    }
  ],
  "predictions": {
    "snapshot": [],
    "log": []
  },
  "ledger": [
    {
      "date": "2025-10-01",
      "symbol": "RIGL",
      "action": "SELL",
      "quantity": -504.0,
      "price": 28.04
    },
    {
      "date": "2025-10-01",
      "symbol": "SPHR",
      "action": "BUY",
      "quantity": 214.0,
      "price": 65.99
    }
  ],
  "meta": {
    "year": 2025,
    "month": "October",
    "month_num": 10,
    "return_pct": 0.00642588995636255,
    "ending_equity": 9243.740000000005,
    "start_date": "2025-10-01",
    "end_date": "2025-10-31"
  }
}