{
  "ticker": "SHCO",
  "name": "SHCO",
  "sector": "Unknown",
  "description": "Investment Thesis available in report.",
  "history": [
    {
      "date": "2024-09-03",
      "open": 6.2,
      "high": 6.2,
      "low": 5.38,
      "close": 5.6
    },
    {
      "date": "2024-09-04",
      "open": 5.49,
      "high": 5.68,
      "low": 5.365,
      "close": 5.51
    },
    {
      "date": "2024-09-05",
      "open": 5.49,
      "high": 5.605,
      "low": 5.37,
      "close": 5.58
    },
    {
      "date": "2024-09-06",
      "open": 5.59,
      "high": 5.9,
      "low": 5.59,
      "close": 5.88
    },
    {
      "date": "2024-09-09",
      "open": 5.87,
      "high": 5.89,
      "low": 5.38,
      "close": 5.44
    },
    {
      "date": "2024-09-10",
      "open": 5.43,
      "high": 5.43,
      "low": 5.07,
      "close": 5.36
    },
    {
      "date": "2024-09-11",
      "open": 5.35,
      "high": 5.49,
      "low": 5.19,
      "close": 5.46
    },
    {
      "date": "2024-09-12",
      "open": 5.44,
      "high": 5.45,
      "low": 5.33,
      "close": 5.37
    },
    {
      "date": "2024-09-13",
      "open": 5.41,
      "high": 5.62,
      "low": 5.335,
      "close": 5.37
    },
    {
      "date": "2024-09-16",
      "open": 5.33,
      "high": 5.4,
      "low": 5.26,
      "close": 5.31
    },
    {
      "date": "2024-09-17",
      "open": 5.34,
      "high": 5.445,
      "low": 5.22,
      "close": 5.24
    },
    {
      "date": "2024-09-18",
      "open": 5.29,
      "high": 5.34,
      "low": 5.16,
      "close": 5.17
    },
    {
      "date": "2024-09-19",
      "open": 5.31,
      "high": 5.33,
      "low": 5.19,
      "close": 5.27
    },
    {
      "date": "2024-09-20",
      "open": 5.24,
      "high": 5.31,
      "low": 5.06,
      "close": 5.12
    },
    {
      "date": "2024-09-23",
      "open": 5.11,
      "high": 5.23,
      "low": 5.02,
      "close": 5.08
    },
    {
      "date": "2024-09-24",
      "open": 5.09,
      "high": 5.25,
      "low": 5.05,
      "close": 5.16
    },
    {
      "date": "2024-09-25",
      "open": 5.18,
      "high": 5.18,
      "low": 4.83,
      "close": 4.87
    },
    {
      "date": "2024-09-26",
      "open": 4.95,
      "high": 5.1,
      "low": 4.89,
      "close": 4.92
    },
    {
      "date": "2024-09-27",
      "open": 5.0,
      "high": 5.4,
      "low": 4.98,
      "close": 5.39
    },
    {
      "date": "2024-09-30",
      "open": 5.33,
      "high": 5.39,
      "low": 5.07,
      "close": 5.1
    },
    {
      "date": "2024-10-01",
      "open": 5.12,
      "high": 5.16,
      "low": 4.98,
      "close": 5.0
    },
    {
      "date": "2024-10-02",
      "open": 4.98,
      "high": 5.13,
      "low": 4.98,
      "close": 5.11
    },
    {
      "date": "2024-10-03",
      "open": 5.08,
      "high": 5.19,
      "low": 5.06,
      "close": 5.15
    },
    {
      "date": "2024-10-04",
      "open": 5.2,
      "high": 5.34,
      "low": 5.19,
      "close": 5.29
    },
    {
      "date": "2024-10-07",
      "open": 5.34,
      "high": 5.34,
      "low": 5.12,
      "close": 5.24
    },
    {
      "date": "2024-10-08",
      "open": 5.21,
      "high": 5.31,
      "low": 5.07,
      "close": 5.07
    },
    {
      "date": "2024-10-09",
      "open": 5.02,
      "high": 5.19,
      "low": 5.01,
      "close": 5.06
    },
    {
      "date": "2024-10-10",
      "open": 4.99,
      "high": 5.17,
      "low": 4.95,
      "close": 5.14
    },
    {
      "date": "2024-10-11",
      "open": 5.14,
      "high": 5.235,
      "low": 5.05,
      "close": 5.07
    },
    {
      "date": "2024-10-14",
      "open": 5.05,
      "high": 5.315,
      "low": 4.9814,
      "close": 5.31
    },
    {
      "date": "2024-10-15",
      "open": 5.31,
      "high": 5.46,
      "low": 5.25,
      "close": 5.39
    },
    {
      "date": "2024-10-16",
      "open": 5.42,
      "high": 5.57,
      "low": 5.3501,
      "close": 5.56
    },
    {
      "date": "2024-10-17",
      "open": 5.58,
      "high": 5.64,
      "low": 5.38,
      "close": 5.4
    },
    {
      "date": "2024-10-18",
      "open": 5.41,
      "high": 5.56,
      "low": 5.349,
      "close": 5.46
    },
    {
      "date": "2024-10-21",
      "open": 5.46,
      "high": 5.5399,
      "low": 5.35,
      "close": 5.42
    },
    {
      "date": "2024-10-22",
      "open": 5.37,
      "high": 5.57,
      "low": 5.35,
      "close": 5.51
    },
    {
      "date": "2024-10-23",
      "open": 5.49,
      "high": 5.515,
      "low": 5.17,
      "close": 5.19
    },
    {
      "date": "2024-10-24",
      "open": 5.18,
      "high": 5.33,
      "low": 5.175,
      "close": 5.29
    },
    {
      "date": "2024-10-25",
      "open": 5.29,
      "high": 5.45,
      "low": 5.2618,
      "close": 5.3
    },
    {
      "date": "2024-10-28",
      "open": 5.45,
      "high": 5.5,
      "low": 5.29,
      "close": 5.33
    },
    {
      "date": "2024-10-29",
      "open": 5.38,
      "high": 5.44,
      "low": 5.34,
      "close": 5.37
    },
    {
      "date": "2024-10-30",
      "open": 5.41,
      "high": 5.49,
      "low": 5.31,
      "close": 5.39
    },
    {
      "date": "2024-10-31",
      "open": 5.41,
      "high": 5.41,
      "low": 5.2,
      "close": 5.31
    },
    {
      "date": "2024-11-01",
      "open": 5.3,
      "high": 5.44,
      "low": 5.22,
      "close": 5.4
    },
    {
      "date": "2024-11-04",
      "open": 5.33,
      "high": 5.405,
      "low": 5.28,
      "close": 5.34
    },
    {
      "date": "2024-11-05",
      "open": 5.31,
      "high": 5.43,
      "low": 5.26,
      "close": 5.38
    },
    {
      "date": "2024-11-06",
      "open": 5.51,
      "high": 5.6,
      "low": 5.38,
      "close": 5.54
    },
    {
      "date": "2024-11-07",
      "open": 5.53,
      "high": 5.5699,
      "low": 5.44,
      "close": 5.52
    },
    {
      "date": "2024-11-08",
      "open": 5.49,
      "high": 5.608,
      "low": 5.38,
      "close": 5.45
    },
    {
      "date": "2024-11-11",
      "open": 5.47,
      "high": 5.5,
      "low": 5.33,
      "close": 5.45
    },
    {
      "date": "2024-11-12",
      "open": 5.33,
      "high": 5.43,
      "low": 5.25,
      "close": 5.32
    },
    {
      "date": "2024-11-13",
      "open": 5.33,
      "high": 5.42,
      "low": 5.28,
      "close": 5.41
    },
    {
      "date": "2024-11-14",
      "open": 5.39,
      "high": 5.5,
      "low": 5.25,
      "close": 5.39
    },
    {
      "date": "2024-11-15",
      "open": 5.41,
      "high": 5.41,
      "low": 5.08,
      "close": 5.13
    },
    {
      "date": "2024-11-18",
      "open": 5.15,
      "high": 5.15,
      "low": 4.9,
      "close": 5.05
    },
    {
      "date": "2024-11-19",
      "open": 5.01,
      "high": 5.1,
      "low": 4.88,
      "close": 4.93
    },
    {
      "date": "2024-11-20",
      "open": 4.9,
      "high": 4.94,
      "low": 4.76,
      "close": 4.76
    },
    {
      "date": "2024-11-21",
      "open": 4.73,
      "high": 5.08,
      "low": 4.73,
      "close": 5.06
    },
    {
      "date": "2024-11-22",
      "open": 5.12,
      "high": 5.16,
      "low": 4.97,
      "close": 5.04
    },
    {
      "date": "2024-11-25",
      "open": 5.04,
      "high": 5.1399,
      "low": 4.905,
      "close": 5.01
    },
    {
      "date": "2024-11-26",
      "open": 5.04,
      "high": 5.07,
      "low": 4.8,
      "close": 4.81
    },
    {
      "date": "2024-11-27",
      "open": 4.95,
      "high": 5.13,
      "low": 4.795,
      "close": 5.03
    },
    {
      "date": "2024-11-29",
      "open": 5.06,
      "high": 5.15,
      "low": 5.0,
      "close": 5.0
    },
    {
      "date": "2024-12-02",
      "open": 5.0,
      "high": 5.105,
      "low": 4.95,
      "close": 5.04
    },
    {
      "date": "2024-12-03",
      "open": 5.05,
      "high": 5.07,
      "low": 4.93,
      "close": 5.04
    },
    {
      "date": "2024-12-04",
      "open": 5.02,
      "high": 5.08,
      "low": 4.96,
      "close": 5.02
    },
    {
      "date": "2024-12-05",
      "open": 5.01,
      "high": 5.0799,
      "low": 4.742,
      "close": 4.75
    },
    {
      "date": "2024-12-06",
      "open": 4.86,
      "high": 4.9299,
      "low": 4.74,
      "close": 4.82
    },
    {
      "date": "2024-12-09",
      "open": 4.87,
      "high": 4.87,
      "low": 4.63,
      "close": 4.71
    },
    {
      "date": "2024-12-10",
      "open": 4.72,
      "high": 4.89,
      "low": 4.6,
      "close": 4.86
    },
    {
      "date": "2024-12-11",
      "open": 4.94,
      "high": 5.005,
      "low": 4.75,
      "close": 4.97
    },
    {
      "date": "2024-12-12",
      "open": 4.88,
      "high": 5.06,
      "low": 4.88,
      "close": 4.99
    },
    {
      "date": "2024-12-13",
      "open": 5.0,
      "high": 5.04,
      "low": 4.87,
      "close": 4.96
    },
    {
      "date": "2024-12-16",
      "open": 4.91,
      "high": 5.08,
      "low": 4.86,
      "close": 5.04
    },
    {
      "date": "2024-12-17",
      "open": 5.04,
      "high": 5.1482,
      "low": 4.98,
      "close": 5.05
    },
    {
      "date": "2024-12-18",
      "open": 5.05,
      "high": 5.15,
      "low": 4.87,
      "close": 4.91
    },
    {
      "date": "2024-12-19",
      "open": 7.89,
      "high": 8.09,
      "low": 7.19,
      "close": 7.22
    },
    {
      "date": "2024-12-20",
      "open": 7.31,
      "high": 7.84,
      "low": 6.82,
      "close": 7.07
    },
    {
      "date": "2024-12-23",
      "open": 7.15,
      "high": 7.7,
      "low": 7.15,
      "close": 7.49
    },
    {
      "date": "2024-12-24",
      "open": 7.49,
      "high": 7.525,
      "low": 7.09,
      "close": 7.17
    },
    {
      "date": "2024-12-26",
      "open": 7.12,
      "high": 7.55,
      "low": 6.8501,
      "close": 7.47
    },
    {
      "date": "2024-12-27",
      "open": 7.39,
      "high": 7.84,
      "low": 7.18,
      "close": 7.59
    },
    {
      "date": "2024-12-30",
      "open": 7.52,
      "high": 7.7,
      "low": 7.43,
      "close": 7.5
    },
    {
      "date": "2024-12-31",
      "open": 7.47,
      "high": 7.62,
      "low": 7.39,
      "close": 7.45
    },
    {
      "date": "2025-01-02",
      "open": 7.47,
      "high": 7.55,
      "low": 7.01,
      "close": 7.4
    },
    {
      "date": "2025-01-03",
      "open": 7.42,
      "high": 7.55,
      "low": 7.28,
      "close": 7.44
    },
    {
      "date": "2025-01-06",
      "open": 7.41,
      "high": 7.65,
      "low": 7.4,
      "close": 7.62
    },
    {
      "date": "2025-01-07",
      "open": 7.7,
      "high": 7.7072,
      "low": 7.5408,
      "close": 7.66
    },
    {
      "date": "2025-01-08",
      "open": 7.59,
      "high": 7.71,
      "low": 7.53,
      "close": 7.64
    },
    {
      "date": "2025-01-10",
      "open": 7.58,
      "high": 7.7,
      "low": 7.52,
      "close": 7.66
    },
    {
      "date": "2025-01-13",
      "open": 7.65,
      "high": 7.81,
      "low": 7.564,
      "close": 7.77
    },
    {
      "date": "2025-01-14",
      "open": 7.78,
      "high": 8.0,
      "low": 7.3,
      "close": 7.65
    },
    {
      "date": "2025-01-15",
      "open": 7.74,
      "high": 7.915,
      "low": 7.51,
      "close": 7.76
    },
    {
      "date": "2025-01-16",
      "open": 7.81,
      "high": 7.81,
      "low": 7.49,
      "close": 7.64
    },
    {
      "date": "2025-01-17",
      "open": 7.66,
      "high": 7.77,
      "low": 7.4,
      "close": 7.53
    },
    {
      "date": "2025-01-21",
      "open": 7.48,
      "high": 7.8,
      "low": 7.45,
      "close": 7.79
    },
    {
      "date": "2025-01-22",
      "open": 7.7,
      "high": 7.805,
      "low": 7.6,
      "close": 7.73
    },
    {
      "date": "2025-01-23",
      "open": 7.69,
      "high": 7.69,
      "low": 7.47,
      "close": 7.56
    },
    {
      "date": "2025-01-24",
      "open": 7.54,
      "high": 7.75,
      "low": 7.5,
      "close": 7.68
    },
    {
      "date": "2025-01-27",
      "open": 7.6,
      "high": 7.72,
      "low": 7.42,
      "close": 7.45
    },
    {
      "date": "2025-01-28",
      "open": 7.38,
      "high": 7.54,
      "low": 7.3301,
      "close": 7.37
    },
    {
      "date": "2025-01-29",
      "open": 7.77,
      "high": 8.47,
      "low": 7.615,
      "close": 8.29
    },
    {
      "date": "2025-01-30",
      "open": 8.34,
      "high": 8.34,
      "low": 7.9,
      "close": 7.98
    },
    {
      "date": "2025-01-31",
      "open": 7.8,
      "high": 8.17,
      "low": 7.8,
      "close": 7.87
    },
    {
      "date": "2025-02-03",
      "open": 7.8,
      "high": 7.99,
      "low": 7.71,
      "close": 7.73
    },
    {
      "date": "2025-02-04",
      "open": 7.7,
      "high": 7.86,
      "low": 7.5815,
      "close": 7.64
    },
    {
      "date": "2025-02-05",
      "open": 7.75,
      "high": 7.775,
      "low": 7.55,
      "close": 7.59
    },
    {
      "date": "2025-02-06",
      "open": 7.59,
      "high": 7.8,
      "low": 7.56,
      "close": 7.77
    },
    {
      "date": "2025-02-07",
      "open": 7.7,
      "high": 7.85,
      "low": 7.54,
      "close": 7.79
    },
    {
      "date": "2025-02-10",
      "open": 7.8,
      "high": 7.97,
      "low": 7.75,
      "close": 7.9
    },
    {
      "date": "2025-02-11",
      "open": 7.85,
      "high": 7.965,
      "low": 7.7734,
      "close": 7.86
    },
    {
      "date": "2025-02-12",
      "open": 7.8,
      "high": 7.98,
      "low": 7.71,
      "close": 7.91
    },
    {
      "date": "2025-02-13",
      "open": 7.96,
      "high": 7.96,
      "low": 7.76,
      "close": 7.92
    },
    {
      "date": "2025-02-14",
      "open": 7.9,
      "high": 7.925,
      "low": 7.84,
      "close": 7.88
    },
    {
      "date": "2025-02-18",
      "open": 7.8,
      "high": 7.965,
      "low": 7.75,
      "close": 7.77
    },
    {
      "date": "2025-02-19",
      "open": 7.82,
      "high": 7.82,
      "low": 7.7,
      "close": 7.78
    },
    {
      "date": "2025-02-20",
      "open": 7.83,
      "high": 7.83,
      "low": 7.63,
      "close": 7.69
    },
    {
      "date": "2025-02-21",
      "open": 7.72,
      "high": 7.72,
      "low": 7.55,
      "close": 7.59
    },
    {
      "date": "2025-02-24",
      "open": 7.55,
      "high": 7.63,
      "low": 7.42,
      "close": 7.58
    },
    {
      "date": "2025-02-25",
      "open": 7.53,
      "high": 7.635,
      "low": 7.49,
      "close": 7.56
    },
    {
      "date": "2025-02-26",
      "open": 7.59,
      "high": 7.65,
      "low": 7.425,
      "close": 7.46
    },
    {
      "date": "2025-02-27",
      "open": 7.53,
      "high": 7.53,
      "low": 7.265,
      "close": 7.29
    },
    {
      "date": "2025-02-28",
      "open": 7.26,
      "high": 7.39,
      "low": 6.84,
      "close": 7.04
    },
    {
      "date": "2025-03-03",
      "open": 7.06,
      "high": 7.06,
      "low": 6.55,
      "close": 6.6
    },
    {
      "date": "2025-03-04",
      "open": 6.6,
      "high": 6.61,
      "low": 6.2,
      "close": 6.34
    },
    {
      "date": "2025-03-05",
      "open": 6.58,
      "high": 6.6,
      "low": 6.34,
      "close": 6.56
    },
    {
      "date": "2025-03-06",
      "open": 6.42,
      "high": 6.7,
      "low": 6.3452,
      "close": 6.41
    },
    {
      "date": "2025-03-07",
      "open": 6.37,
      "high": 6.505,
      "low": 6.37,
      "close": 6.41
    },
    {
      "date": "2025-03-10",
      "open": 6.29,
      "high": 6.44,
      "low": 6.0,
      "close": 6.06
    },
    {
      "date": "2025-03-11",
      "open": 6.0,
      "high": 6.08,
      "low": 5.83,
      "close": 5.87
    },
    {
      "date": "2025-03-12",
      "open": 5.94,
      "high": 5.95,
      "low": 5.44,
      "close": 5.48
    },
    {
      "date": "2025-03-13",
      "open": 5.42,
      "high": 5.58,
      "low": 5.15,
      "close": 5.19
    },
    {
      "date": "2025-03-14",
      "open": 5.3,
      "high": 6.03,
      "low": 5.28,
      "close": 5.94
    },
    {
      "date": "2025-03-17",
      "open": 5.88,
      "high": 6.57,
      "low": 5.88,
      "close": 6.49
    },
    {
      "date": "2025-03-18",
      "open": 6.42,
      "high": 6.7,
      "low": 6.26,
      "close": 6.67
    },
    {
      "date": "2025-03-19",
      "open": 7.02,
      "high": 7.28,
      "low": 6.73,
      "close": 7.27
    },
    {
      "date": "2025-03-20",
      "open": 7.14,
      "high": 7.3199,
      "low": 6.97,
      "close": 6.99
    },
    {
      "date": "2025-03-21",
      "open": 6.88,
      "high": 7.1213,
      "low": 6.69,
      "close": 7.08
    },
    {
      "date": "2025-03-24",
      "open": 7.16,
      "high": 7.16,
      "low": 6.965,
      "close": 7.05
    },
    {
      "date": "2025-03-25",
      "open": 6.95,
      "high": 7.02,
      "low": 6.54,
      "close": 6.6
    },
    {
      "date": "2025-03-26",
      "open": 6.57,
      "high": 6.77,
      "low": 6.45,
      "close": 6.59
    },
    {
      "date": "2025-03-27",
      "open": 6.51,
      "high": 6.72,
      "low": 6.45,
      "close": 6.72
    },
    {
      "date": "2025-03-28",
      "open": 6.66,
      "high": 6.8382,
      "low": 6.15,
      "close": 6.24
    },
    {
      "date": "2025-03-31",
      "open": 6.1,
      "high": 6.3,
      "low": 6.04,
      "close": 6.18
    },
    {
      "date": "2025-04-01",
      "open": 5.76,
      "high": 6.74,
      "low": 5.65,
      "close": 6.37
    },
    {
      "date": "2025-04-02",
      "open": 6.23,
      "high": 6.4399,
      "low": 6.13,
      "close": 6.23
    },
    {
      "date": "2025-04-03",
      "open": 5.92,
      "high": 6.11,
      "low": 5.83,
      "close": 5.91
    },
    {
      "date": "2025-04-04",
      "open": 5.68,
      "high": 5.81,
      "low": 5.19,
      "close": 5.31
    },
    {
      "date": "2025-04-07",
      "open": 5.04,
      "high": 5.47,
      "low": 4.88,
      "close": 5.08
    },
    {
      "date": "2025-04-08",
      "open": 5.3,
      "high": 5.47,
      "low": 4.95,
      "close": 4.96
    },
    {
      "date": "2025-04-09",
      "open": 4.97,
      "high": 5.87,
      "low": 4.77,
      "close": 5.8
    },
    {
      "date": "2025-04-10",
      "open": 5.62,
      "high": 5.75,
      "low": 5.0,
      "close": 5.09
    },
    {
      "date": "2025-04-11",
      "open": 5.12,
      "high": 5.28,
      "low": 5.02,
      "close": 5.23
    },
    {
      "date": "2025-04-14",
      "open": 5.36,
      "high": 5.36,
      "low": 5.125,
      "close": 5.25
    },
    {
      "date": "2025-04-15",
      "open": 5.29,
      "high": 5.375,
      "low": 5.085,
      "close": 5.14
    },
    {
      "date": "2025-04-16",
      "open": 5.17,
      "high": 5.24,
      "low": 5.02,
      "close": 5.09
    },
    {
      "date": "2025-04-17",
      "open": 5.09,
      "high": 5.19,
      "low": 5.09,
      "close": 5.11
    },
    {
      "date": "2025-04-21",
      "open": 5.04,
      "high": 5.18,
      "low": 5.02,
      "close": 5.1
    },
    {
      "date": "2025-04-22",
      "open": 5.19,
      "high": 5.41,
      "low": 5.19,
      "close": 5.28
    },
    {
      "date": "2025-04-23",
      "open": 5.46,
      "high": 5.6199,
      "low": 5.39,
      "close": 5.44
    },
    {
      "date": "2025-04-24",
      "open": 5.44,
      "high": 5.78,
      "low": 5.3579,
      "close": 5.72
    },
    {
      "date": "2025-04-25",
      "open": 5.7,
      "high": 5.965,
      "low": 5.683,
      "close": 5.9
    },
    {
      "date": "2025-04-28",
      "open": 5.89,
      "high": 6.0,
      "low": 5.68,
      "close": 5.8
    },
    {
      "date": "2025-04-29",
      "open": 5.8,
      "high": 5.98,
      "low": 5.7,
      "close": 5.94
    },
    {
      "date": "2025-04-30",
      "open": 5.81,
      "high": 6.16,
      "low": 5.81,
      "close": 6.01
    },
    {
      "date": "2025-05-01",
      "open": 6.05,
      "high": 6.39,
      "low": 5.99,
      "close": 6.23
    },
    {
      "date": "2025-05-02",
      "open": 6.32,
      "high": 6.58,
      "low": 6.26,
      "close": 6.37
    },
    {
      "date": "2025-05-05",
      "open": 6.3,
      "high": 6.34,
      "low": 6.05,
      "close": 6.1
    },
    {
      "date": "2025-05-06",
      "open": 5.99,
      "high": 6.14,
      "low": 5.99,
      "close": 6.07
    },
    {
      "date": "2025-05-07",
      "open": 6.09,
      "high": 6.35,
      "low": 6.02,
      "close": 6.33
    },
    {
      "date": "2025-05-08",
      "open": 6.41,
      "high": 6.41,
      "low": 6.12,
      "close": 6.16
    },
    {
      "date": "2025-05-09",
      "open": 6.75,
      "high": 6.75,
      "low": 5.82,
      "close": 5.97
    },
    {
      "date": "2025-05-12",
      "open": 6.21,
      "high": 6.49,
      "low": 6.18,
      "close": 6.35
    },
    {
      "date": "2025-05-13",
      "open": 6.35,
      "high": 6.43,
      "low": 6.26,
      "close": 6.26
    },
    {
      "date": "2025-05-14",
      "open": 6.27,
      "high": 6.43,
      "low": 6.25,
      "close": 6.32
    },
    {
      "date": "2025-05-15",
      "open": 6.31,
      "high": 6.55,
      "low": 6.1701,
      "close": 6.42
    },
    {
      "date": "2025-05-16",
      "open": 6.42,
      "high": 6.84,
      "low": 6.42,
      "close": 6.76
    },
    {
      "date": "2025-05-19",
      "open": 6.64,
      "high": 6.7692,
      "low": 6.58,
      "close": 6.62
    },
    {
      "date": "2025-05-20",
      "open": 6.6,
      "high": 6.62,
      "low": 6.34,
      "close": 6.44
    },
    {
      "date": "2025-05-21",
      "open": 6.33,
      "high": 6.48,
      "low": 6.17,
      "close": 6.22
    },
    {
      "date": "2025-05-22",
      "open": 6.22,
      "high": 6.34,
      "low": 6.2,
      "close": 6.26
    },
    {
      "date": "2025-05-23",
      "open": 6.1,
      "high": 6.38,
      "low": 6.1,
      "close": 6.32
    },
    {
      "date": "2025-05-27",
      "open": 6.47,
      "high": 6.652,
      "low": 6.41,
      "close": 6.59
    },
    {
      "date": "2025-05-28",
      "open": 6.6,
      "high": 6.64,
      "low": 6.48,
      "close": 6.5
    },
    {
      "date": "2025-05-29",
      "open": 6.54,
      "high": 6.59,
      "low": 6.34,
      "close": 6.36
    },
    {
      "date": "2025-05-30",
      "open": 6.34,
      "high": 6.41,
      "low": 6.2523,
      "close": 6.31
    },
    {
      "date": "2025-06-02",
      "open": 6.29,
      "high": 6.45,
      "low": 6.21,
      "close": 6.25
    },
    {
      "date": "2025-06-03",
      "open": 6.21,
      "high": 6.435,
      "low": 6.21,
      "close": 6.34
    },
    {
      "date": "2025-06-04",
      "open": 6.37,
      "high": 6.47,
      "low": 6.32,
      "close": 6.46
    },
    {
      "date": "2025-06-05",
      "open": 6.47,
      "high": 6.52,
      "low": 6.34,
      "close": 6.4
    },
    {
      "date": "2025-06-06",
      "open": 6.48,
      "high": 6.5133,
      "low": 6.26,
      "close": 6.27
    },
    {
      "date": "2025-06-09",
      "open": 6.31,
      "high": 6.5,
      "low": 6.31,
      "close": 6.42
    },
    {
      "date": "2025-06-10",
      "open": 6.5,
      "high": 6.58,
      "low": 6.3618,
      "close": 6.53
    },
    {
      "date": "2025-06-11",
      "open": 6.55,
      "high": 6.71,
      "low": 6.35,
      "close": 6.69
    },
    {
      "date": "2025-06-12",
      "open": 6.6,
      "high": 6.77,
      "low": 6.4311,
      "close": 6.71
    },
    {
      "date": "2025-06-13",
      "open": 6.66,
      "high": 6.7178,
      "low": 6.55,
      "close": 6.68
    },
    {
      "date": "2025-06-16",
      "open": 6.75,
      "high": 7.1,
      "low": 6.63,
      "close": 7.08
    },
    {
      "date": "2025-06-17",
      "open": 7.0,
      "high": 7.0424,
      "low": 6.86,
      "close": 6.94
    },
    {
      "date": "2025-06-18",
      "open": 6.95,
      "high": 7.0,
      "low": 6.84,
      "close": 6.88
    },
    {
      "date": "2025-06-20",
      "open": 6.93,
      "high": 7.13,
      "low": 6.93,
      "close": 7.04
    },
    {
      "date": "2025-06-23",
      "open": 7.0,
      "high": 7.17,
      "low": 6.75,
      "close": 7.07
    },
    {
      "date": "2025-06-24",
      "open": 7.16,
      "high": 7.36,
      "low": 7.09,
      "close": 7.14
    },
    {
      "date": "2025-06-25",
      "open": 7.17,
      "high": 7.3,
      "low": 7.1,
      "close": 7.28
    },
    {
      "date": "2025-06-26",
      "open": 7.33,
      "high": 7.46,
      "low": 7.215,
      "close": 7.35
    },
    {
      "date": "2025-06-27",
      "open": 7.37,
      "high": 7.45,
      "low": 7.2144,
      "close": 7.35
    },
    {
      "date": "2025-06-30",
      "open": 7.38,
      "high": 7.45,
      "low": 7.3,
      "close": 7.35
    },
    {
      "date": "2025-07-01",
      "open": 7.33,
      "high": 7.68,
      "low": 7.32,
      "close": 7.65
    },
    {
      "date": "2025-07-02",
      "open": 7.6,
      "high": 7.74,
      "low": 7.45,
      "close": 7.72
    },
    {
      "date": "2025-07-03",
      "open": 7.75,
      "high": 7.81,
      "low": 7.64,
      "close": 7.65
    },
    {
      "date": "2025-07-07",
      "open": 7.61,
      "high": 7.68,
      "low": 7.41,
      "close": 7.53
    },
    {
      "date": "2025-07-08",
      "open": 7.57,
      "high": 7.71,
      "low": 7.47,
      "close": 7.54
    },
    {
      "date": "2025-07-09",
      "open": 7.57,
      "high": 7.64,
      "low": 7.25,
      "close": 7.35
    },
    {
      "date": "2025-07-10",
      "open": 7.32,
      "high": 7.46,
      "low": 7.25,
      "close": 7.45
    },
    {
      "date": "2025-07-11",
      "open": 7.4,
      "high": 7.4789,
      "low": 7.1011,
      "close": 7.24
    },
    {
      "date": "2025-07-14",
      "open": 7.2,
      "high": 7.21,
      "low": 6.95,
      "close": 7.06
    },
    {
      "date": "2025-07-15",
      "open": 7.11,
      "high": 7.15,
      "low": 6.82,
      "close": 6.88
    },
    {
      "date": "2025-07-16",
      "open": 6.92,
      "high": 7.08,
      "low": 6.79,
      "close": 6.83
    },
    {
      "date": "2025-07-17",
      "open": 6.84,
      "high": 6.935,
      "low": 6.72,
      "close": 6.73
    },
    {
      "date": "2025-07-18",
      "open": 6.8,
      "high": 6.9,
      "low": 6.67,
      "close": 6.86
    },
    {
      "date": "2025-07-21",
      "open": 6.86,
      "high": 6.86,
      "low": 6.44,
      "close": 6.49
    },
    {
      "date": "2025-07-22",
      "open": 6.42,
      "high": 6.45,
      "low": 6.24,
      "close": 6.38
    },
    {
      "date": "2025-07-23",
      "open": 6.35,
      "high": 6.67,
      "low": 6.3,
      "close": 6.52
    },
    {
      "date": "2025-07-24",
      "open": 6.52,
      "high": 6.75,
      "low": 6.46,
      "close": 6.46
    },
    {
      "date": "2025-07-25",
      "open": 6.48,
      "high": 6.63,
      "low": 6.43,
      "close": 6.54
    },
    {
      "date": "2025-07-28",
      "open": 6.54,
      "high": 6.5799,
      "low": 6.4,
      "close": 6.41
    },
    {
      "date": "2025-07-29",
      "open": 6.37,
      "high": 6.53,
      "low": 6.3,
      "close": 6.51
    },
    {
      "date": "2025-07-30",
      "open": 6.54,
      "high": 6.5781,
      "low": 6.35,
      "close": 6.37
    },
    {
      "date": "2025-07-31",
      "open": 6.36,
      "high": 6.53,
      "low": 6.31,
      "close": 6.35
    },
    {
      "date": "2025-08-01",
      "open": 6.3,
      "high": 6.33,
      "low": 6.12,
      "close": 6.31
    },
    {
      "date": "2025-08-04",
      "open": 6.35,
      "high": 6.53,
      "low": 6.3454,
      "close": 6.51
    },
    {
      "date": "2025-08-05",
      "open": 6.57,
      "high": 6.685,
      "low": 6.39,
      "close": 6.64
    },
    {
      "date": "2025-08-06",
      "open": 6.62,
      "high": 6.62,
      "low": 6.42,
      "close": 6.49
    },
    {
      "date": "2025-08-07",
      "open": 6.52,
      "high": 6.56,
      "low": 6.29,
      "close": 6.51
    },
    {
      "date": "2025-08-08",
      "open": 7.5,
      "high": 7.5,
      "low": 6.81,
      "close": 7.29
    },
    {
      "date": "2025-08-11",
      "open": 7.39,
      "high": 7.4,
      "low": 7.205,
      "close": 7.27
    },
    {
      "date": "2025-08-12",
      "open": 7.28,
      "high": 7.61,
      "low": 7.26,
      "close": 7.47
    },
    {
      "date": "2025-08-13",
      "open": 7.57,
      "high": 7.795,
      "low": 7.5,
      "close": 7.66
    },
    {
      "date": "2025-08-14",
      "open": 7.64,
      "high": 7.82,
      "low": 7.53,
      "close": 7.81
    },
    {
      "date": "2025-08-15",
      "open": 7.85,
      "high": 7.85,
      "low": 7.63,
      "close": 7.64
    },
    {
      "date": "2025-08-18",
      "open": 8.865,
      "high": 8.88,
      "low": 8.755,
      "close": 8.78
    },
    {
      "date": "2025-08-19",
      "open": 8.8,
      "high": 8.815,
      "low": 8.78,
      "close": 8.78
    },
    {
      "date": "2025-08-20",
      "open": 8.8,
      "high": 8.8,
      "low": 8.77,
      "close": 8.79
    },
    {
      "date": "2025-08-21",
      "open": 8.78,
      "high": 8.8,
      "low": 8.78,
      "close": 8.8
    },
    {
      "date": "2025-08-22",
      "open": 8.82,
      "high": 8.82,
      "low": 8.79,
      "close": 8.8
    },
    {
      "date": "2025-08-25",
      "open": 8.8,
      "high": 8.82,
      "low": 8.79,
      "close": 8.81
    },
    {
      "date": "2025-08-26",
      "open": 8.82,
      "high": 8.83,
      "low": 8.81,
      "close": 8.83
    },
    {
      "date": "2025-08-27",
      "open": 8.82,
      "high": 8.84,
      "low": 8.82,
      "close": 8.84
    },
    {
      "date": "2025-08-28",
      "open": 8.81,
      "high": 8.84,
      "low": 8.81,
      "close": 8.83
    },
    {
      "date": "2025-08-29",
      "open": 8.83,
      "high": 8.84,
      "low": 8.82,
      "close": 8.83
    }
  ],
  "markers": []
}