{
  "ticker": "CRESY",
  "period": "2025-12",
  "candles": [
    {
      "date": "2025-11-24",
      "open": 11.41,
      "high": 11.46,
      "low": 11.03,
      "close": 11.39,
      "volume": 260369
    },
    {
      "date": "2025-11-25",
      "open": 11.69,
      "high": 11.69,
      "low": 11.12,
      "close": 11.37,
      "volume": 415100
    },
    {
      "date": "2025-11-26",
      "open": 11.38,
      "high": 12.365,
      "low": 11.38,
      "close": 12.29,
      "volume": 358931
    },
    {
      "date": "2025-11-28",
      "open": 11.8,
      "high": 12.09,
      "low": 11.64,
      "close": 11.93,
      "volume": 362774
    },
    {
      "date": "2025-12-01",
      "open": 11.71,
      "high": 11.8699,
      "low": 11.4001,
      "close": 11.5,
      "volume": 159290
    },
    {
      "date": "2025-12-02",
      "open": 11.51,
      "high": 11.75,
      "low": 11.25,
      "close": 11.34,
      "volume": 215207
    },
    {
      "date": "2025-12-03",
      "open": 11.27,
      "high": 11.8767,
      "low": 11.27,
      "close": 11.74,
      "volume": 649035
    },
    {
      "date": "2025-12-04",
      "open": 11.84,
      "high": 11.935,
      "low": 11.5601,
      "close": 11.68,
      "volume": 197930
    },
    {
      "date": "2025-12-05",
      "open": 11.7,
      "high": 12.1,
      "low": 11.35,
      "close": 11.49,
      "volume": 241003
    },
    {
      "date": "2025-12-08",
      "open": 11.5,
      "high": 11.673,
      "low": 11.23,
      "close": 11.37,
      "volume": 100114
    },
    {
      "date": "2025-12-09",
      "open": 11.4,
      "high": 11.528,
      "low": 11.25,
      "close": 11.33,
      "volume": 114873
    },
    {
      "date": "2025-12-10",
      "open": 11.26,
      "high": 11.81,
      "low": 11.26,
      "close": 11.68,
      "volume": 377749
    },
    {
      "date": "2025-12-11",
      "open": 11.65,
      "high": 11.68,
      "low": 11.3,
      "close": 11.56,
      "volume": 323327
    },
    {
      "date": "2025-12-12",
      "open": 11.56,
      "high": 11.935,
      "low": 11.5,
      "close": 11.83,
      "volume": 325100
    },
    {
      "date": "2025-12-15",
      "open": 11.83,
      "high": 11.8784,
      "low": 11.63,
      "close": 11.74,
      "volume": 198828
    },
    {
      "date": "2025-12-16",
      "open": 11.74,
      "high": 11.74,
      "low": 11.12,
      "close": 11.26,
      "volume": 229967
    },
    {
      "date": "2025-12-17",
      "open": 11.35,
      "high": 11.52,
      "low": 11.31,
      "close": 11.4,
      "volume": 149042
    },
    {
      "date": "2025-12-18",
      "open": 11.45,
      "high": 11.95,
      "low": 11.4137,
      "close": 11.76,
      "volume": 456140
    },
    {
      "date": "2025-12-19",
      "open": 11.77,
      "high": 11.94,
      "low": 11.36,
      "close": 11.73,
      "volume": 551834
    },
    {
      "date": "2025-12-22",
      "open": 11.71,
      "high": 11.95,
      "low": 11.6,
      "close": 11.61,
      "volume": 428574
    },
    {
      "date": "2025-12-23",
      "open": 11.66,
      "high": 12.0,
      "low": 11.615,
      "close": 11.68,
      "volume": 317151
    },
    {
      "date": "2025-12-24",
      "open": 11.73,
      "high": 11.78,
      "low": 11.5382,
      "close": 11.69,
      "volume": 107702
    },
    {
      "date": "2025-12-26",
      "open": 11.69,
      "high": 11.87,
      "low": 11.63,
      "close": 11.83,
      "volume": 211149
    },
    {
      "date": "2025-12-29",
      "open": 11.8,
      "high": 12.4393,
      "low": 11.7852,
      "close": 12.39,
      "volume": 408454
    },
    {
      "date": "2025-12-30",
      "open": 12.505,
      "high": 12.74,
      "low": 12.3,
      "close": 12.65,
      "volume": 445355
    },
    {
      "date": "2025-12-31",
      "open": 12.56,
      "high": 12.7,
      "low": 12.38,
      "close": 12.63,
      "volume": 245716
    }
  ],
  "events": [
    {
      "date": "2025-11-25",
      "type": "BUY",
      "price": 11.69,
      "quantity": 1394
    },
    {
      "date": "2025-12-03",
      "type": "SELL",
      "price": 11.27,
      "quantity": -1394
    }
  ]
}